Workbook

Sheet 资产负债表
C1: =MAX(资产!A:A) -> 46162
C3: =CONCATENATE(" 美联储资产负债表（",YEAR($C$1),"年",MONTH($C$1),"月",DAY($C$1),"日）") -> 美联储资产负债表（2026年5月20日） | G3: 单位：亿美元 | I3: 日期 | J3: 美国国债 | K3: 短期债券 | L3: 中长期名义债券 | M3: 1年以内 | N3: 1-5年 | O3: 5-10年 | P3: 大于10年 | Q3: 抵押贷款支持债券(MBS) | R3: 存款准备金 | S3: 美国财政部一般账户(TGA) | T3: 总资产 | U3: 持有债券 | V3: 逆回购协议 | W3: 美国财政存款 | X3: 总负债 | Y3: 净流动性 | Z3: 联储总资产-逆回购协议-美国财政存款
A4: 0 | C4: 总资产 | D4: =VLOOKUP($C$1,资产!$A:$AF,2,0)/100 -> 67136.43 | F4: 总负债 | G4: =VLOOKUP($C$1,负债!$A:$P,2,0)/100 -> 66664.07 | I4: 43831 | J4: =VLOOKUP(I4,资产!$A:$AF,8,0)/100 -> 23289.33 | K4: =VLOOKUP(I4,资产!$A:$AF,9,0)/100 -> 1695.25 | L4: =VLOOKUP(I4,资产!$A:$AF,10,0)/100 -> 20065.5 | M4: =(VLOOKUP(I4,资产!$A:$AF,13,0)+VLOOKUP(I4,资产!$A:$AF,14,0)+VLOOKUP(I4,资产!$A:$AF,15,0))/100 -> 4658.24 | N4: =VLOOKUP(I4,资产!$A:$AF,16,0)/100 -> 9009.72 | O4: =VLOOKUP(I4,资产!$A:$AF,17,0)/100 -> 3215.91 | P4: =VLOOKUP(I4,资产!$A:$AF,18,0)/100 -> 6405.47 | Q4: =VLOOKUP(I4,资产!$A:$AF,20,0)/100 -> 14086.77 | R4: =VLOOKUP(I4,负债!$A:$P,5,0)/100 -> 15488.49 | S4: =VLOOKUP(I4,负债!$A:$P,6,0)/100 -> 4038.53 | T4: =VLOOKUP(I4,资产!$A:$AF,2,0)/100 -> 41736.26 | U4: =VLOOKUP(I4,资产!$A:$AF,7,0)/100 -> 37399.57 | V4: =VLOOKUP(I4,负债!$A:$P,9,0)/100 -> 3366.49 | W4: =VLOOKUP(I4,负债!$A:$P,6,0)/100 -> 4038.53 | X4: =VLOOKUP(I4,负债!$A:$P,2,0)/100 -> 41351.03 | Y4: =T4-V4-W4 -> 34331.24
A5: 1 | C5: * 黄金证券账户 | D5: =VLOOKUP($C$1,资产!$A:$AF,3,0)/100 -> 110.37 | F5: * 存款 | G5: =VLOOKUP($C$1,负债!$A:$P,3,0)/100 -> 41445.76 | I5: 43838 | J5: =VLOOKUP(I5,资产!$A:$AF,8,0)/100 -> 23477.14 | K5: =VLOOKUP(I5,资产!$A:$AF,9,0)/100 -> 1845.27 | L5: =VLOOKUP(I5,资产!$A:$AF,10,0)/100 -> 20103.5 | M5: =(VLOOKUP(I5,资产!$A:$AF,13,0)+VLOOKUP(I5,资产!$A:$AF,14,0)+VLOOKUP(I5,资产!$A:$AF,15,0))/100 -> 4879.64 | N5: =VLOOKUP(I5,资产!$A:$AF,16,0)/100 -> 8948.5 | O5: =VLOOKUP(I5,资产!$A:$AF,17,0)/100 -> 3243.01 | P5: =VLOOKUP(I5,资产!$A:$AF,18,0)/100 -> 6405.99 | Q5: =VLOOKUP(I5,资产!$A:$AF,20,0)/100 -> 14086.77 | R5: =VLOOKUP(I5,负债!$A:$P,5,0)/100 -> 16566.29 | S5: =VLOOKUP(I5,负债!$A:$P,6,0)/100 -> 3508.4 | T5: =VLOOKUP(I5,资产!$A:$AF,2,0)/100 -> 41495.44 | U5: =VLOOKUP(I5,资产!$A:$AF,7,0)/100 -> 37587.38 | V5: =VLOOKUP(I5,负债!$A:$P,9,0)/100 -> 2749.23 | W5: =VLOOKUP(I5,负债!$A:$P,6,0)/100 -> 3508.4 | X5: =VLOOKUP(I5,负债!$A:$P,2,0)/100 -> 41110.21 | Y5: =T5-V5-W5 -> 35237.81
A6: 1 | C6: * 特别提款权账户 | D6: =VLOOKUP($C$1,资产!$A:$AF,4,0)/100 -> 152 | F6: * 存款机构定期存款 | G6: =VLOOKUP($C$1,负债!$A:$P,4,0)/100 -> 0 | I6: 43845 | J6: =VLOOKUP(I6,资产!$A:$AF,8,0)/100 -> 23626.35 | K6: =VLOOKUP(I6,资产!$A:$AF,9,0)/100 -> 1950.29 | L6: =VLOOKUP(I6,资产!$A:$AF,10,0)/100 -> 20141.16 | M6: =(VLOOKUP(I6,资产!$A:$AF,13,0)+VLOOKUP(I6,资产!$A:$AF,14,0)+VLOOKUP(I6,资产!$A:$AF,15,0))/100 -> 4959.69 | N6: =VLOOKUP(I6,资产!$A:$AF,16,0)/100 -> 9077.5 | O6: =VLOOKUP(I6,资产!$A:$AF,17,0)/100 -> 3156.12 | P6: =VLOOKUP(I6,资产!$A:$AF,18,0)/100 -> 6433.04 | Q6: =VLOOKUP(I6,资产!$A:$AF,20,0)/100 -> 14043.18 | R6: =VLOOKUP(I6,负债!$A:$P,5,0)/100 -> 16733.62 | S6: =VLOOKUP(I6,负债!$A:$P,6,0)/100 -> 3808.02 | T6: =VLOOKUP(I6,资产!$A:$AF,2,0)/100 -> 41758.5 | U6: =VLOOKUP(I6,资产!$A:$AF,7,0)/100 -> 37693 | V6: =VLOOKUP(I6,负债!$A:$P,9,0)/100 -> 2609.13 | W6: =VLOOKUP(I6,负债!$A:$P,6,0)/100 -> 3808.02 | X6: =VLOOKUP(I6,负债!$A:$P,2,0)/100 -> 41373.27 | Y6: =T6-V6-W6 -> 35341.35
A7: 1 | C7: * 硬币 | D7: =VLOOKUP($C$1,资产!$A:$AF,5,0)/100 -> 14.05 | F7: * 存款准备金 | G7: =VLOOKUP($C$1,负债!$A:$P,5,0)/100 -> 31067.16 | I7: 43852 | J7: =VLOOKUP(I7,资产!$A:$AF,8,0)/100 -> 23810.2 | K7: =VLOOKUP(I7,资产!$A:$AF,9,0)/100 -> 2100.31 | L7: =VLOOKUP(I7,资产!$A:$AF,10,0)/100 -> 20175.18 | M7: =(VLOOKUP(I7,资产!$A:$AF,13,0)+VLOOKUP(I7,资产!$A:$AF,14,0)+VLOOKUP(I7,资产!$A:$AF,15,0))/100 -> 5195 | N7: =VLOOKUP(I7,资产!$A:$AF,16,0)/100 -> 9026.19 | O7: =VLOOKUP(I7,资产!$A:$AF,17,0)/100 -> 3156.05 | P7: =VLOOKUP(I7,资产!$A:$AF,18,0)/100 -> 6432.97 | Q7: =VLOOKUP(I7,资产!$A:$AF,20,0)/100 -> 13986.42 | R7: =VLOOKUP(I7,负债!$A:$P,5,0)/100 -> 16095.94 | S7: =VLOOKUP(I7,负债!$A:$P,6,0)/100 -> 4117.08 | T7: =VLOOKUP(I7,资产!$A:$AF,2,0)/100 -> 41459.12 | U7: =VLOOKUP(I7,资产!$A:$AF,7,0)/100 -> 37820.1 | V7: =VLOOKUP(I7,负债!$A:$P,9,0)/100 -> 2653.57 | W7: =VLOOKUP(I7,负债!$A:$P,6,0)/100 -> 4117.08 | X7: =VLOOKUP(I7,负债!$A:$P,2,0)/100 -> 41073.9 | Y7: =T7-V7-W7 -> 34688.47
A8: 1 | C8: * 持有证券、未摊销证券溢价和折扣、回购协议和贷款 | D8: =VLOOKUP($C$1,资产!$A:$AF,6,0)/100 -> 66342.67 | F8: * 美国财政部一般账户(TGA) | G8: =VLOOKUP($C$1,负债!$A:$P,6,0)/100 -> 7819.79 | I8: 43859 | J8: =VLOOKUP(I8,资产!$A:$AF,8,0)/100 -> 24091.08 | K8: =VLOOKUP(I8,资产!$A:$AF,9,0)/100 -> 2325.34 | L8: =VLOOKUP(I8,资产!$A:$AF,10,0)/100 -> 20231.21 | M8: =(VLOOKUP(I8,资产!$A:$AF,13,0)+VLOOKUP(I8,资产!$A:$AF,14,0)+VLOOKUP(I8,资产!$A:$AF,15,0))/100 -> 5420.01 | N8: =VLOOKUP(I8,资产!$A:$AF,16,0)/100 -> 9082.19 | O8: =VLOOKUP(I8,资产!$A:$AF,17,0)/100 -> 3155.98 | P8: =VLOOKUP(I8,资产!$A:$AF,18,0)/100 -> 6432.9 | Q8: =VLOOKUP(I8,资产!$A:$AF,20,0)/100 -> 13872.88 | R8: =VLOOKUP(I8,负债!$A:$P,5,0)/100 -> 16122.23 | S8: =VLOOKUP(I8,负债!$A:$P,6,0)/100 -> 4505.37 | T8: =VLOOKUP(I8,资产!$A:$AF,2,0)/100 -> 41516.3 | U8: =VLOOKUP(I8,资产!$A:$AF,7,0)/100 -> 37987.43 | V8: =VLOOKUP(I8,负债!$A:$P,9,0)/100 -> 2334.04 | W8: =VLOOKUP(I8,负债!$A:$P,6,0)/100 -> 4505.37 | X8: =VLOOKUP(I8,负债!$A:$P,2,0)/100 -> 41131.08 | Y8: =T8-V8-W8 -> 34676.89
A9: 2 | C9: * 持有证券 | D9: =VLOOKUP($C$1,资产!$A:$AF,7,0)/100 -> 64377.19 | F9: * 外国官方 | G9: =VLOOKUP($C$1,负债!$A:$P,7,0)/100 -> 94.43 | I9: 43866 | J9: =VLOOKUP(I9,资产!$A:$AF,8,0)/100 -> 24278.8 | K9: =VLOOKUP(I9,资产!$A:$AF,9,0)/100 -> 2475.36 | L9: =VLOOKUP(I9,资产!$A:$AF,10,0)/100 -> 20254.75 | M9: =(VLOOKUP(I9,资产!$A:$AF,13,0)+VLOOKUP(I9,资产!$A:$AF,14,0)+VLOOKUP(I9,资产!$A:$AF,15,0))/100 -> 5471.78 | N9: =VLOOKUP(I9,资产!$A:$AF,16,0)/100 -> 9179.55 | O9: =VLOOKUP(I9,资产!$A:$AF,17,0)/100 -> 3193.29 | P9: =VLOOKUP(I9,资产!$A:$AF,18,0)/100 -> 6434.19 | Q9: =VLOOKUP(I9,资产!$A:$AF,20,0)/100 -> 13872.89 | R9: =VLOOKUP(I9,负债!$A:$P,5,0)/100 -> 16528.73 | S9: =VLOOKUP(I9,负债!$A:$P,6,0)/100 -> 4165.85 | T9: =VLOOKUP(I9,资产!$A:$AF,2,0)/100 -> 41667.07 | U9: =VLOOKUP(I9,资产!$A:$AF,7,0)/100 -> 38175.16 | V9: =VLOOKUP(I9,负债!$A:$P,9,0)/100 -> 2391.63 | W9: =VLOOKUP(I9,负债!$A:$P,6,0)/100 -> 4165.85 | X9: =VLOOKUP(I9,负债!$A:$P,2,0)/100 -> 41282.05 | Y9: =T9-V9-W9 -> 35109.59
A10: 3 | C10: * 美国国债 | D10: =VLOOKUP($C$1,资产!$A:$AF,8,0)/100 -> 44577.12 | F10: * 其他存款 | G10: =VLOOKUP($C$1,负债!$A:$P,8,0)/100 -> 2464.38 | I10: 43873 | J10: =VLOOKUP(I10,资产!$A:$AF,8,0)/100 -> 24426.21 | K10: =VLOOKUP(I10,资产!$A:$AF,9,0)/100 -> 2580.38 | L10: =VLOOKUP(I10,资产!$A:$AF,10,0)/100 -> 20280.77 | M10: =(VLOOKUP(I10,资产!$A:$AF,13,0)+VLOOKUP(I10,资产!$A:$AF,14,0)+VLOOKUP(I10,资产!$A:$AF,15,0))/100 -> 5576.77 | N10: =VLOOKUP(I10,资产!$A:$AF,16,0)/100 -> 9183.5 | O10: =VLOOKUP(I10,资产!$A:$AF,17,0)/100 -> 3193.15 | P10: =VLOOKUP(I10,资产!$A:$AF,18,0)/100 -> 6472.78 | Q10: =VLOOKUP(I10,资产!$A:$AF,20,0)/100 -> 13915.26 | R10: =VLOOKUP(I10,负债!$A:$P,5,0)/100 -> 16950.82 | S10: =VLOOKUP(I10,负债!$A:$P,6,0)/100 -> 4043.41 | T10: =VLOOKUP(I10,资产!$A:$AF,2,0)/100 -> 41826.89 | U10: =VLOOKUP(I10,资产!$A:$AF,7,0)/100 -> 38364.94 | V10: =VLOOKUP(I10,负债!$A:$P,9,0)/100 -> 2238.29 | W10: =VLOOKUP(I10,负债!$A:$P,6,0)/100 -> 4043.41 | X10: =VLOOKUP(I10,负债!$A:$P,2,0)/100 -> 41441.69 | Y10: =T10-V10-W10 -> 35545.19
A11: 3 | C11: * 联邦机构债券 | D11: =VLOOKUP($C$1,资产!$A:$AF,19,0)/100 -> 23.47 | F11: * 逆向回购协议 | G11: =VLOOKUP($C$1,负债!$A:$P,9,0)/100 -> 3426.28 | I11: 43880 | J11: =VLOOKUP(I11,资产!$A:$AF,8,0)/100 -> 24516.88 | K11: =VLOOKUP(I11,资产!$A:$AF,9,0)/100 -> 2655.39 | L11: =VLOOKUP(I11,资产!$A:$AF,10,0)/100 -> 20296.78 | M11: =(VLOOKUP(I11,资产!$A:$AF,13,0)+VLOOKUP(I11,资产!$A:$AF,14,0)+VLOOKUP(I11,资产!$A:$AF,15,0))/100 -> 5639.9 | N11: =VLOOKUP(I11,资产!$A:$AF,16,0)/100 -> 9065.88 | O11: =VLOOKUP(I11,资产!$A:$AF,17,0)/100 -> 3253.96 | P11: =VLOOKUP(I11,资产!$A:$AF,18,0)/100 -> 6557.15 | Q11: =VLOOKUP(I11,资产!$A:$AF,20,0)/100 -> 13857.84 | R11: =VLOOKUP(I11,负债!$A:$P,5,0)/100 -> 16590.21 | S11: =VLOOKUP(I11,负债!$A:$P,6,0)/100 -> 4210.51 | T11: =VLOOKUP(I11,资产!$A:$AF,2,0)/100 -> 41715.7 | U11: =VLOOKUP(I11,资产!$A:$AF,7,0)/100 -> 38398.19 | V11: =VLOOKUP(I11,负债!$A:$P,9,0)/100 -> 2269.64 | W11: =VLOOKUP(I11,负债!$A:$P,6,0)/100 -> 4210.51 | X11: =VLOOKUP(I11,负债!$A:$P,2,0)/100 -> 41330.25 | Y11: =T11-V11-W11 -> 35235.55
A12: 3 | C12: * 抵押贷款支持债券(MBS) | D12: =VLOOKUP($C$1,资产!$A:$AF,20,0)/100 -> 19776.61 | F12: * 联储票据(扣除美联储自持部分) | G12: =VLOOKUP($C$1,负债!$A:$P,10,0)/100 -> 24103.79 | I12: 43887 | J12: =VLOOKUP(I12,资产!$A:$AF,8,0)/100 -> 24740.6 | K12: =VLOOKUP(I12,资产!$A:$AF,9,0)/100 -> 2805.41 | L12: =VLOOKUP(I12,资产!$A:$AF,10,0)/100 -> 20370.82 | M12: =(VLOOKUP(I12,资产!$A:$AF,13,0)+VLOOKUP(I12,资产!$A:$AF,14,0)+VLOOKUP(I12,资产!$A:$AF,15,0))/100 -> 5795.76 | N12: =VLOOKUP(I12,资产!$A:$AF,16,0)/100 -> 9133.98 | O12: =VLOOKUP(I12,资产!$A:$AF,17,0)/100 -> 3253.82 | P12: =VLOOKUP(I12,资产!$A:$AF,18,0)/100 -> 6557.02 | Q12: =VLOOKUP(I12,资产!$A:$AF,20,0)/100 -> 13718.43 | R12: =VLOOKUP(I12,负债!$A:$P,5,0)/100 -> 16800.7 | S12: =VLOOKUP(I12,负债!$A:$P,6,0)/100 -> 3876.15 | T12: =VLOOKUP(I12,资产!$A:$AF,2,0)/100 -> 41586.37 | U12: =VLOOKUP(I12,资产!$A:$AF,7,0)/100 -> 38482.5 | V12: =VLOOKUP(I12,负债!$A:$P,9,0)/100 -> 2199.68 | W12: =VLOOKUP(I12,负债!$A:$P,6,0)/100 -> 3876.15 | X12: =VLOOKUP(I12,负债!$A:$P,2,0)/100 -> 41200.86 | Y12: =T12-V12-W12 -> 35510.54
A13: 2 | C13: * 当前持有的未摊销证券溢价 | D13: =VLOOKUP($C$1,资产!$A:$AF,21,0)/100 -> 2165.18 | F13: * 延迟入账现金项目 | G13: =VLOOKUP($C$1,负债!$A:$P,11,0)/100 -> 3.16 | I13: 43894 | J13: =VLOOKUP(I13,资产!$A:$AF,8,0)/100 -> 25026.24 | K13: =VLOOKUP(I13,资产!$A:$AF,9,0)/100 -> 3030.42 | L13: =VLOOKUP(I13,资产!$A:$AF,10,0)/100 -> 20430.81 | M13: =(VLOOKUP(I13,资产!$A:$AF,13,0)+VLOOKUP(I13,资产!$A:$AF,14,0)+VLOOKUP(I13,资产!$A:$AF,15,0))/100 -> 6037.8 | N13: =VLOOKUP(I13,资产!$A:$AF,16,0)/100 -> 9143.39 | O13: =VLOOKUP(I13,资产!$A:$AF,17,0)/100 -> 3263.23 | P13: =VLOOKUP(I13,资产!$A:$AF,18,0)/100 -> 6581.81 | Q13: =VLOOKUP(I13,资产!$A:$AF,20,0)/100 -> 13718.46 | R13: =VLOOKUP(I13,负债!$A:$P,5,0)/100 -> 17350.06 | S13: =VLOOKUP(I13,负债!$A:$P,6,0)/100 -> 3813.02 | T13: =VLOOKUP(I13,资产!$A:$AF,2,0)/100 -> 42415.07 | U13: =VLOOKUP(I13,资产!$A:$AF,7,0)/100 -> 38768.16 | V13: =VLOOKUP(I13,负债!$A:$P,9,0)/100 -> 2367.02 | W13: =VLOOKUP(I13,负债!$A:$P,6,0)/100 -> 3813.02 | X13: =VLOOKUP(I13,负债!$A:$P,2,0)/100 -> 42029.49 | Y13: =T13-V13-W13 -> 36235.03
A14: 2 | C14: * 当前持有的未摊销证券折扣 | D14: =VLOOKUP($C$1,资产!$A:$AF,22,0)/100 -> -256.15 | F14: * 财政部对信贷部门的捐助 | G14: =VLOOKUP($C$1,负债!$A:$P,12,0)/100 -> 8.21 | I14: 43901 | J14: =VLOOKUP(I14,资产!$A:$AF,8,0)/100 -> 25230.31 | K14: =VLOOKUP(I14,资产!$A:$AF,9,0)/100 -> 3210.43 | L14: =VLOOKUP(I14,资产!$A:$AF,10,0)/100 -> 20434.82 | M14: =(VLOOKUP(I14,资产!$A:$AF,13,0)+VLOOKUP(I14,资产!$A:$AF,14,0)+VLOOKUP(I14,资产!$A:$AF,15,0))/100 -> 6217.91 | N14: =VLOOKUP(I14,资产!$A:$AF,16,0)/100 -> 9151.01 | O14: =VLOOKUP(I14,资产!$A:$AF,17,0)/100 -> 3279.06 | P14: =VLOOKUP(I14,资产!$A:$AF,18,0)/100 -> 6582.32 | Q14: =VLOOKUP(I14,资产!$A:$AF,20,0)/100 -> 13718.46 | R14: =VLOOKUP(I14,负债!$A:$P,5,0)/100 -> 17799.9 | S14: =VLOOKUP(I14,负债!$A:$P,6,0)/100 -> 3723.37 | T14: =VLOOKUP(I14,资产!$A:$AF,2,0)/100 -> 43119.11 | U14: =VLOOKUP(I14,资产!$A:$AF,7,0)/100 -> 38972.24 | V14: =VLOOKUP(I14,负债!$A:$P,9,0)/100 -> 2332.75 | W14: =VLOOKUP(I14,负债!$A:$P,6,0)/100 -> 3723.37 | X14: =VLOOKUP(I14,负债!$A:$P,2,0)/100 -> 42733.17 | Y14: =T14-V14-W14 -> 37062.99
A15: 2 | C15: * 正向回购协议 | D15: =VLOOKUP($C$1,资产!$A:$AF,23,0)/100 -> 0.07 | F15: * 其他负债及应计股息 | G15: =VLOOKUP($C$1,负债!$A:$P,13,0)/100 -> -2323.14 | I15: 43908 | J15: =VLOOKUP(I15,资产!$A:$AF,8,0)/100 -> 26407.71 | K15: =VLOOKUP(I15,资产!$A:$AF,9,0)/100 -> 3210.43 | L15: =VLOOKUP(I15,资产!$A:$AF,10,0)/100 -> 21544.96 | M15: =(VLOOKUP(I15,资产!$A:$AF,13,0)+VLOOKUP(I15,资产!$A:$AF,14,0)+VLOOKUP(I15,资产!$A:$AF,15,0))/100 -> 6343.52 | N15: =VLOOKUP(I15,资产!$A:$AF,16,0)/100 -> 9667.62 | O15: =VLOOKUP(I15,资产!$A:$AF,17,0)/100 -> 3576.66 | P15: =VLOOKUP(I15,资产!$A:$AF,18,0)/100 -> 6819.91 | Q15: =VLOOKUP(I15,资产!$A:$AF,20,0)/100 -> 13666.76 | R15: =VLOOKUP(I15,负债!$A:$P,5,0)/100 -> 19453.94 | S15: =VLOOKUP(I15,负债!$A:$P,6,0)/100 -> 4013.54 | T15: =VLOOKUP(I15,资产!$A:$AF,2,0)/100 -> 46682.12 | U15: =VLOOKUP(I15,资产!$A:$AF,7,0)/100 -> 40097.94 | V15: =VLOOKUP(I15,负债!$A:$P,9,0)/100 -> 2339.46 | W15: =VLOOKUP(I15,负债!$A:$P,6,0)/100 -> 4013.54 | X15: =VLOOKUP(I15,负债!$A:$P,2,0)/100 -> 46296.04 | Y15: =T15-V15-W15 -> 40329.12
A16: 2 | C16: * 其他贷款 | D16: =VLOOKUP($C$1,资产!$A:$AF,24,0)/100 -> 56.37 | I16: 43915 | J16: =VLOOKUP(I16,资产!$A:$AF,8,0)/100 -> 29783.72 | K16: =VLOOKUP(I16,资产!$A:$AF,9,0)/100 -> 3260.44 | L16: =VLOOKUP(I16,资产!$A:$AF,10,0)/100 -> 24561.25 | M16: =(VLOOKUP(I16,资产!$A:$AF,13,0)+VLOOKUP(I16,资产!$A:$AF,14,0)+VLOOKUP(I16,资产!$A:$AF,15,0))/100 -> 6951.55 | N16: =VLOOKUP(I16,资产!$A:$AF,16,0)/100 -> 11111.45 | O16: =VLOOKUP(I16,资产!$A:$AF,17,0)/100 -> 4363.18 | P16: =VLOOKUP(I16,资产!$A:$AF,18,0)/100 -> 7357.54 | Q16: =VLOOKUP(I16,资产!$A:$AF,20,0)/100 -> 13845.63 | R16: =VLOOKUP(I16,负债!$A:$P,5,0)/100 -> 23477.47 | S16: =VLOOKUP(I16,负债!$A:$P,6,0)/100 -> 3848.9 | T16: =VLOOKUP(I16,资产!$A:$AF,2,0)/100 -> 52542.78 | U16: =VLOOKUP(I16,资产!$A:$AF,7,0)/100 -> 43652.82 | V16: =VLOOKUP(I16,负债!$A:$P,9,0)/100 -> 3591.14 | W16: =VLOOKUP(I16,负债!$A:$P,6,0)/100 -> 3848.9 | X16: =VLOOKUP(I16,负债!$A:$P,2,0)/100 -> 52154.83 | Y16: =T16-V16-W16 -> 45102.74
A17: 1 | C17: * MS Facilities LLC的净投资组合持有量(中产阶级贷款计划) | D17: =VLOOKUP($C$1,资产!$A:$AF,25,0)/100 -> 14.2 | I17: 43922 | J17: =VLOOKUP(I17,资产!$A:$AF,8,0)/100 -> 33408.32 | K17: =VLOOKUP(I17,资产!$A:$AF,9,0)/100 -> 3260.44 | L17: =VLOOKUP(I17,资产!$A:$AF,10,0)/100 -> 27918.6 | M17: =(VLOOKUP(I17,资产!$A:$AF,13,0)+VLOOKUP(I17,资产!$A:$AF,14,0)+VLOOKUP(I17,资产!$A:$AF,15,0))/100 -> 7373.1 | N17: =VLOOKUP(I17,资产!$A:$AF,16,0)/100 -> 12983.45 | O17: =VLOOKUP(I17,资产!$A:$AF,17,0)/100 -> 5092.28 | P17: =VLOOKUP(I17,资产!$A:$AF,18,0)/100 -> 7959.49 | Q17: =VLOOKUP(I17,资产!$A:$AF,20,0)/100 -> 14577.21 | R17: =VLOOKUP(I17,负债!$A:$P,5,0)/100 -> 26843.98 | S17: =VLOOKUP(I17,负债!$A:$P,6,0)/100 -> 5069.33 | T17: =VLOOKUP(I17,资产!$A:$AF,2,0)/100 -> 58116.07 | U17: =VLOOKUP(I17,资产!$A:$AF,7,0)/100 -> 48009.01 | V17: =VLOOKUP(I17,负债!$A:$P,9,0)/100 -> 4944.27 | W17: =VLOOKUP(I17,负债!$A:$P,6,0)/100 -> 5069.33 | X17: =VLOOKUP(I17,负债!$A:$P,2,0)/100 -> 57727.8 | Y17: =T17-V17-W17 -> 48102.47
A18: 1 | C18: * 市政流动性基金有限责任公司持有的净投资组合 | D18: =VLOOKUP($C$1,资产!$A:$AF,26,0)/100 -> 0 | F18: 全部资本（净资产） | G18: =VLOOKUP($C$1,负债!$A:$Q,17,0)/100 -> 472.36 | I18: 43929 | J18: =VLOOKUP(I18,资产!$A:$AF,8,0)/100 -> 36343.86 | K18: =VLOOKUP(I18,资产!$A:$AF,9,0)/100 -> 3260.44 | L18: =VLOOKUP(I18,资产!$A:$AF,10,0)/100 -> 30648.6 | M18: =(VLOOKUP(I18,资产!$A:$AF,13,0)+VLOOKUP(I18,资产!$A:$AF,14,0)+VLOOKUP(I18,资产!$A:$AF,15,0))/100 -> 7811.16 | N18: =VLOOKUP(I18,资产!$A:$AF,16,0)/100 -> 14322.06 | O18: =VLOOKUP(I18,资产!$A:$AF,17,0)/100 -> 5769.18 | P18: =VLOOKUP(I18,资产!$A:$AF,18,0)/100 -> 8441.46 | Q18: =VLOOKUP(I18,资产!$A:$AF,20,0)/100 -> 14597.01 | R18: =VLOOKUP(I18,负债!$A:$P,5,0)/100 -> 27745.06 | S18: =VLOOKUP(I18,负债!$A:$P,6,0)/100 -> 8271.78 | T18: =VLOOKUP(I18,资产!$A:$AF,2,0)/100 -> 60831.41 | U18: =VLOOKUP(I18,资产!$A:$AF,7,0)/100 -> 50964.34 | V18: =VLOOKUP(I18,负债!$A:$P,9,0)/100 -> 3344.88 | W18: =VLOOKUP(I18,负债!$A:$P,6,0)/100 -> 8271.78 | X18: =VLOOKUP(I18,负债!$A:$P,2,0)/100 -> 60443.09 | Y18: =T18-V18-W18 -> 49214.75
A19: 1 | C19: * 持有TALF II LLC投资组合净额 | D19: =VLOOKUP($C$1,资产!$A:$AF,27,0)/100 -> 0 | F19: * 实缴资本 | G19: =VLOOKUP($C$1,负债!$A:$P,14,0)/100 -> 404.51 | I19: 43936 | J19: =VLOOKUP(I19,资产!$A:$AF,8,0)/100 -> 37888.58 | K19: =VLOOKUP(I19,资产!$A:$AF,9,0)/100 -> 3260.44 | L19: =VLOOKUP(I19,资产!$A:$AF,10,0)/100 -> 32061.44 | M19: =(VLOOKUP(I19,资产!$A:$AF,13,0)+VLOOKUP(I19,资产!$A:$AF,14,0)+VLOOKUP(I19,资产!$A:$AF,15,0))/100 -> 8112.8 | N19: =VLOOKUP(I19,资产!$A:$AF,16,0)/100 -> 14933.36 | O19: =VLOOKUP(I19,资产!$A:$AF,17,0)/100 -> 6212.55 | P19: =VLOOKUP(I19,资产!$A:$AF,18,0)/100 -> 8629.87 | Q19: =VLOOKUP(I19,资产!$A:$AF,20,0)/100 -> 15681.71 | R19: =VLOOKUP(I19,负债!$A:$P,5,0)/100 -> 30698.74 | S19: =VLOOKUP(I19,负债!$A:$P,6,0)/100 -> 8561.55 | T19: =VLOOKUP(I19,资产!$A:$AF,2,0)/100 -> 63678.87 | U19: =VLOOKUP(I19,资产!$A:$AF,7,0)/100 -> 53593.76 | V19: =VLOOKUP(I19,负债!$A:$P,9,0)/100 -> 2795.84 | W19: =VLOOKUP(I19,负债!$A:$P,6,0)/100 -> 8561.55 | X19: =VLOOKUP(I19,负债!$A:$P,2,0)/100 -> 63290.55 | Y19: =T19-V19-W19 -> 52321.48
A20: 1 | C20: * 托收中项目 | D20: =VLOOKUP($C$1,资产!$A:$AF,28,0)/100 -> 0.53 | F20: * 结余 | G20: =VLOOKUP($C$1,负债!$A:$P,15,0)/100 -> 67.85 | I20: 43943 | J20: =VLOOKUP(I20,资产!$A:$AF,8,0)/100 -> 39093.52 | K20: =VLOOKUP(I20,资产!$A:$AF,9,0)/100 -> 3260.44 | L20: =VLOOKUP(I20,资产!$A:$AF,10,0)/100 -> 33146.44 | M20: =(VLOOKUP(I20,资产!$A:$AF,13,0)+VLOOKUP(I20,资产!$A:$AF,14,0)+VLOOKUP(I20,资产!$A:$AF,15,0))/100 -> 8306.53 | N20: =VLOOKUP(I20,资产!$A:$AF,16,0)/100 -> 15363.92 | O20: =VLOOKUP(I20,资产!$A:$AF,17,0)/100 -> 6593.09 | P20: =VLOOKUP(I20,资产!$A:$AF,18,0)/100 -> 8829.97 | Q20: =VLOOKUP(I20,资产!$A:$AF,20,0)/100 -> 16224.87 | R20: =VLOOKUP(I20,负债!$A:$P,5,0)/100 -> 30999.8 | S20: =VLOOKUP(I20,负债!$A:$P,6,0)/100 -> 9499.99 | T20: =VLOOKUP(I20,资产!$A:$AF,2,0)/100 -> 65731.36 | U20: =VLOOKUP(I20,资产!$A:$AF,7,0)/100 -> 55341.86 | V20: =VLOOKUP(I20,负债!$A:$P,9,0)/100 -> 2892.92 | W20: =VLOOKUP(I20,负债!$A:$P,6,0)/100 -> 9499.99 | X20: =VLOOKUP(I20,负债!$A:$P,2,0)/100 -> 65343.04 | Y20: =T20-V20-W20 -> 53338.45
A21: 1 | C21: * 银行不动产 | D21: =VLOOKUP($C$1,资产!$A:$AF,29,0)/100 -> 6.69 | F21: * 其他资本账户 | G21: =VLOOKUP($C$1,负债!$A:$P,16,0)/100 -> 0 | I21: 43950 | J21: =VLOOKUP(I21,资产!$A:$AF,8,0)/100 -> 39714.19 | K21: =VLOOKUP(I21,资产!$A:$AF,9,0)/100 -> 3260.44 | L21: =VLOOKUP(I21,资产!$A:$AF,10,0)/100 -> 33670.47 | M21: =(VLOOKUP(I21,资产!$A:$AF,13,0)+VLOOKUP(I21,资产!$A:$AF,14,0)+VLOOKUP(I21,资产!$A:$AF,15,0))/100 -> 8409.71 | N21: =VLOOKUP(I21,资产!$A:$AF,16,0)/100 -> 15724.72 | O21: =VLOOKUP(I21,资产!$A:$AF,17,0)/100 -> 6655.96 | P21: =VLOOKUP(I21,资产!$A:$AF,18,0)/100 -> 8923.81 | Q21: =VLOOKUP(I21,资产!$A:$AF,20,0)/100 -> 16047.2 | R21: =VLOOKUP(I21,负债!$A:$P,5,0)/100 -> 31635.13 | S21: =VLOOKUP(I21,负债!$A:$P,6,0)/100 -> 10762.32 | T21: =VLOOKUP(I21,资产!$A:$AF,2,0)/100 -> 66559.29 | U21: =VLOOKUP(I21,资产!$A:$AF,7,0)/100 -> 55784.86 | V21: =VLOOKUP(I21,负债!$A:$P,9,0)/100 -> 2691.06 | W21: =VLOOKUP(I21,负债!$A:$P,6,0)/100 -> 10762.32 | X21: =VLOOKUP(I21,负债!$A:$P,2,0)/100 -> 66170.91 | Y21: =T21-V21-W21 -> 53105.91
A22: 1 | C22: * 中央银行流动性互换 | D22: =VLOOKUP($C$1,资产!$A:$AF,30,0)/100 -> 0.16 | I22: 43957 | J22: =VLOOKUP(I22,资产!$A:$AF,8,0)/100 -> 40201.91 | K22: =VLOOKUP(I22,资产!$A:$AF,9,0)/100 -> 3260.44 | L22: =VLOOKUP(I22,资产!$A:$AF,10,0)/100 -> 34095.16 | M22: =(VLOOKUP(I22,资产!$A:$AF,13,0)+VLOOKUP(I22,资产!$A:$AF,14,0)+VLOOKUP(I22,资产!$A:$AF,15,0))/100 -> 8769.13 | N22: =VLOOKUP(I22,资产!$A:$AF,16,0)/100 -> 15685.84 | O22: =VLOOKUP(I22,资产!$A:$AF,17,0)/100 -> 6758.1 | P22: =VLOOKUP(I22,资产!$A:$AF,18,0)/100 -> 8988.85 | Q22: =VLOOKUP(I22,资产!$A:$AF,20,0)/100 -> 16053.8 | R22: =VLOOKUP(I22,负债!$A:$P,5,0)/100 -> 31656.06 | S22: =VLOOKUP(I22,负债!$A:$P,6,0)/100 -> 11432.68 | T22: =VLOOKUP(I22,资产!$A:$AF,2,0)/100 -> 67214.2 | U22: =VLOOKUP(I22,资产!$A:$AF,7,0)/100 -> 56279.18 | V22: =VLOOKUP(I22,负债!$A:$P,9,0)/100 -> 2652.06 | W22: =VLOOKUP(I22,负债!$A:$P,6,0)/100 -> 11432.68 | X22: =VLOOKUP(I22,负债!$A:$P,2,0)/100 -> 66825.49 | Y22: =T22-V22-W22 -> 53129.46
A23: 1 | C23: * 外币 | D23: =VLOOKUP($C$1,资产!$A:$AF,31,0)/100 -> 192.43 | I23: 43964 | J23: =VLOOKUP(I23,资产!$A:$AF,8,0)/100 -> 40572.68 | K23: =VLOOKUP(I23,资产!$A:$AF,9,0)/100 -> 3260.44 | L23: =VLOOKUP(I23,资产!$A:$AF,10,0)/100 -> 34426.16 | M23: =(VLOOKUP(I23,资产!$A:$AF,13,0)+VLOOKUP(I23,资产!$A:$AF,14,0)+VLOOKUP(I23,资产!$A:$AF,15,0))/100 -> 8817.85 | N23: =VLOOKUP(I23,资产!$A:$AF,16,0)/100 -> 15844.94 | O23: =VLOOKUP(I23,资产!$A:$AF,17,0)/100 -> 6866.28 | P23: =VLOOKUP(I23,资产!$A:$AF,18,0)/100 -> 9043.61 | Q23: =VLOOKUP(I23,资产!$A:$AF,20,0)/100 -> 17837.61 | R23: =VLOOKUP(I23,负债!$A:$P,5,0)/100 -> 32634.31 | S23: =VLOOKUP(I23,负债!$A:$P,6,0)/100 -> 11381.72 | T23: =VLOOKUP(I23,资产!$A:$AF,2,0)/100 -> 69342.27 | U23: =VLOOKUP(I23,资产!$A:$AF,7,0)/100 -> 58433.76 | V23: =VLOOKUP(I23,负债!$A:$P,9,0)/100 -> 2811.5 | W23: =VLOOKUP(I23,负债!$A:$P,6,0)/100 -> 11381.72 | X23: =VLOOKUP(I23,负债!$A:$P,2,0)/100 -> 68953.36 | Y23: =T23-V23-W23 -> 55149.05
A24: 1 | C24: * 其他联储资产 | D24: =VLOOKUP($C$1,资产!$A:$AF,32,0)/100 -> 303.33 | I24: 43971 | J24: =VLOOKUP(I24,资产!$A:$AF,8,0)/100 -> 40893.31 | K24: =VLOOKUP(I24,资产!$A:$AF,9,0)/100 -> 3260.44 | L24: =VLOOKUP(I24,资产!$A:$AF,10,0)/100 -> 34712.24 | M24: =(VLOOKUP(I24,资产!$A:$AF,13,0)+VLOOKUP(I24,资产!$A:$AF,14,0)+VLOOKUP(I24,资产!$A:$AF,15,0))/100 -> 8988.77 | N24: =VLOOKUP(I24,资产!$A:$AF,16,0)/100 -> 15680.66 | O24: =VLOOKUP(I24,资产!$A:$AF,17,0)/100 -> 7112.58 | P24: =VLOOKUP(I24,资产!$A:$AF,18,0)/100 -> 9111.3 | Q24: =VLOOKUP(I24,资产!$A:$AF,20,0)/100 -> 18628.41 | R24: =VLOOKUP(I24,负债!$A:$P,5,0)/100 -> 33042.21 | S24: =VLOOKUP(I24,负债!$A:$P,6,0)/100 -> 11932.97 | T24: =VLOOKUP(I24,资产!$A:$AF,2,0)/100 -> 70372.58 | U24: =VLOOKUP(I24,资产!$A:$AF,7,0)/100 -> 59545.18 | V24: =VLOOKUP(I24,负债!$A:$P,9,0)/100 -> 2666.49 | W24: =VLOOKUP(I24,负债!$A:$P,6,0)/100 -> 11932.97 | X24: =VLOOKUP(I24,负债!$A:$P,2,0)/100 -> 69983.65 | Y24: =T24-V24-W24 -> 55773.12
I25: 43978 | J25: =VLOOKUP(I25,资产!$A:$AF,8,0)/100 -> 41095.12 | K25: =VLOOKUP(I25,资产!$A:$AF,9,0)/100 -> 3260.44 | L25: =VLOOKUP(I25,资产!$A:$AF,10,0)/100 -> 34891.74 | M25: =(VLOOKUP(I25,资产!$A:$AF,13,0)+VLOOKUP(I25,资产!$A:$AF,14,0)+VLOOKUP(I25,资产!$A:$AF,15,0))/100 -> 8988.67 | N25: =VLOOKUP(I25,资产!$A:$AF,16,0)/100 -> 15775.52 | O25: =VLOOKUP(I25,资产!$A:$AF,17,0)/100 -> 7199.15 | P25: =VLOOKUP(I25,资产!$A:$AF,18,0)/100 -> 9131.77 | Q25: =VLOOKUP(I25,资产!$A:$AF,20,0)/100 -> 18351.1 | R25: =VLOOKUP(I25,负债!$A:$P,5,0)/100 -> 33176.88 | S25: =VLOOKUP(I25,负债!$A:$P,6,0)/100 -> 13268.97 | T25: =VLOOKUP(I25,资产!$A:$AF,2,0)/100 -> 70973.16 | U25: =VLOOKUP(I25,资产!$A:$AF,7,0)/100 -> 59469.69 | V25: =VLOOKUP(I25,负债!$A:$P,9,0)/100 -> 2439.76 | W25: =VLOOKUP(I25,负债!$A:$P,6,0)/100 -> 13268.97 | X25: =VLOOKUP(I25,负债!$A:$P,2,0)/100 -> 70584.02 | Y25: =T25-V25-W25 -> 55264.43
I26: 43985 | J26: =VLOOKUP(I26,资产!$A:$AF,8,0)/100 -> 41343.56 | K26: =VLOOKUP(I26,资产!$A:$AF,9,0)/100 -> 3260.44 | L26: =VLOOKUP(I26,资产!$A:$AF,10,0)/100 -> 35124.24 | M26: =(VLOOKUP(I26,资产!$A:$AF,13,0)+VLOOKUP(I26,资产!$A:$AF,14,0)+VLOOKUP(I26,资产!$A:$AF,15,0))/100 -> 9224.49 | N26: =VLOOKUP(I26,资产!$A:$AF,16,0)/100 -> 15751.73 | O26: =VLOOKUP(I26,资产!$A:$AF,17,0)/100 -> 7193.93 | P26: =VLOOKUP(I26,资产!$A:$AF,18,0)/100 -> 9173.41 | Q26: =VLOOKUP(I26,资产!$A:$AF,20,0)/100 -> 18355.94 | R26: =VLOOKUP(I26,负债!$A:$P,5,0)/100 -> 32574.35 | S26: =VLOOKUP(I26,负债!$A:$P,6,0)/100 -> 14314.62 | T26: =VLOOKUP(I26,资产!$A:$AF,2,0)/100 -> 71652.17 | U26: =VLOOKUP(I26,资产!$A:$AF,7,0)/100 -> 59722.97 | V26: =VLOOKUP(I26,负债!$A:$P,9,0)/100 -> 2460.54 | W26: =VLOOKUP(I26,负债!$A:$P,6,0)/100 -> 14314.62 | X26: =VLOOKUP(I26,负债!$A:$P,2,0)/100 -> 71263 | Y26: =T26-V26-W26 -> 54877.01
I27: 43992 | J27: =VLOOKUP(I27,资产!$A:$AF,8,0)/100 -> 41504.09 | K27: =VLOOKUP(I27,资产!$A:$AF,9,0)/100 -> 3260.44 | L27: =VLOOKUP(I27,资产!$A:$AF,10,0)/100 -> 35267.74 | M27: =(VLOOKUP(I27,资产!$A:$AF,13,0)+VLOOKUP(I27,资产!$A:$AF,14,0)+VLOOKUP(I27,资产!$A:$AF,15,0))/100 -> 9224.18 | N27: =VLOOKUP(I27,资产!$A:$AF,16,0)/100 -> 15810.35 | O27: =VLOOKUP(I27,资产!$A:$AF,17,0)/100 -> 7253.16 | P27: =VLOOKUP(I27,资产!$A:$AF,18,0)/100 -> 9216.4 | Q27: =VLOOKUP(I27,资产!$A:$AF,20,0)/100 -> 18355.95 | R27: =VLOOKUP(I27,负债!$A:$P,5,0)/100 -> 31906.54 | S27: =VLOOKUP(I27,负债!$A:$P,6,0)/100 -> 15045.69 | T27: =VLOOKUP(I27,资产!$A:$AF,2,0)/100 -> 71689.36 | U27: =VLOOKUP(I27,资产!$A:$AF,7,0)/100 -> 59883.51 | V27: =VLOOKUP(I27,负债!$A:$P,9,0)/100 -> 2408.14 | W27: =VLOOKUP(I27,负债!$A:$P,6,0)/100 -> 15045.69 | X27: =VLOOKUP(I27,负债!$A:$P,2,0)/100 -> 71300.21 | Y27: =T27-V27-W27 -> 54235.53
I28: 43999 | J28: =VLOOKUP(I28,资产!$A:$AF,8,0)/100 -> 41693.4 | K28: =VLOOKUP(I28,资产!$A:$AF,9,0)/100 -> 3260.44 | L28: =VLOOKUP(I28,资产!$A:$AF,10,0)/100 -> 35423.89 | M28: =(VLOOKUP(I28,资产!$A:$AF,13,0)+VLOOKUP(I28,资产!$A:$AF,14,0)+VLOOKUP(I28,资产!$A:$AF,15,0))/100 -> 9344.02 | N28: =VLOOKUP(I28,资产!$A:$AF,16,0)/100 -> 15817.75 | O28: =VLOOKUP(I28,资产!$A:$AF,17,0)/100 -> 7291.59 | P28: =VLOOKUP(I28,资产!$A:$AF,18,0)/100 -> 9240.06 | Q28: =VLOOKUP(I28,资产!$A:$AF,20,0)/100 -> 19187.41 | R28: =VLOOKUP(I28,负债!$A:$P,5,0)/100 -> 30694.39 | S28: =VLOOKUP(I28,负债!$A:$P,6,0)/100 -> 15653.06 | T28: =VLOOKUP(I28,资产!$A:$AF,2,0)/100 -> 70946.9 | U28: =VLOOKUP(I28,资产!$A:$AF,7,0)/100 -> 60904.28 | V28: =VLOOKUP(I28,负债!$A:$P,9,0)/100 -> 2254.62 | W28: =VLOOKUP(I28,负债!$A:$P,6,0)/100 -> 15653.06 | X28: =VLOOKUP(I28,负债!$A:$P,2,0)/100 -> 70557.76 | Y28: =T28-V28-W28 -> 53039.22
I29: 44006 | J29: =VLOOKUP(I29,资产!$A:$AF,8,0)/100 -> 41974.04 | K29: =VLOOKUP(I29,资产!$A:$AF,9,0)/100 -> 3260.44 | L29: =VLOOKUP(I29,资产!$A:$AF,10,0)/100 -> 35709.24 | M29: =(VLOOKUP(I29,资产!$A:$AF,13,0)+VLOOKUP(I29,资产!$A:$AF,14,0)+VLOOKUP(I29,资产!$A:$AF,15,0))/100 -> 9434.58 | N29: =VLOOKUP(I29,资产!$A:$AF,16,0)/100 -> 15924.47 | O29: =VLOOKUP(I29,资产!$A:$AF,17,0)/100 -> 7358.83 | P29: =VLOOKUP(I29,资产!$A:$AF,18,0)/100 -> 9256.17 | Q29: =VLOOKUP(I29,资产!$A:$AF,20,0)/100 -> 19434.41 | R29: =VLOOKUP(I29,负债!$A:$P,5,0)/100 -> 29376.57 | S29: =VLOOKUP(I29,负债!$A:$P,6,0)/100 -> 15865.73 | T29: =VLOOKUP(I29,资产!$A:$AF,2,0)/100 -> 70823.02 | U29: =VLOOKUP(I29,资产!$A:$AF,7,0)/100 -> 61431.93 | V29: =VLOOKUP(I29,负债!$A:$P,9,0)/100 -> 2203.62 | W29: =VLOOKUP(I29,负债!$A:$P,6,0)/100 -> 15865.73 | X29: =VLOOKUP(I29,负债!$A:$P,2,0)/100 -> 70433.91 | Y29: =T29-V29-W29 -> 52753.67
I30: 44013 | J30: =VLOOKUP(I30,资产!$A:$AF,8,0)/100 -> 42132.2 | K30: =VLOOKUP(I30,资产!$A:$AF,9,0)/100 -> 3260.44 | L30: =VLOOKUP(I30,资产!$A:$AF,10,0)/100 -> 35811.39 | M30: =(VLOOKUP(I30,资产!$A:$AF,13,0)+VLOOKUP(I30,资产!$A:$AF,14,0)+VLOOKUP(I30,资产!$A:$AF,15,0))/100 -> 9507.51 | N30: =VLOOKUP(I30,资产!$A:$AF,16,0)/100 -> 15979.28 | O30: =VLOOKUP(I30,资产!$A:$AF,17,0)/100 -> 7321.5 | P30: =VLOOKUP(I30,资产!$A:$AF,18,0)/100 -> 9323.91 | Q30: =VLOOKUP(I30,资产!$A:$AF,20,0)/100 -> 19113.81 | R30: =VLOOKUP(I30,负债!$A:$P,5,0)/100 -> 28631.96 | S30: =VLOOKUP(I30,负债!$A:$P,6,0)/100 -> 16567.47 | T30: =VLOOKUP(I30,资产!$A:$AF,2,0)/100 -> 70090.4 | U30: =VLOOKUP(I30,资产!$A:$AF,7,0)/100 -> 61269.48 | V30: =VLOOKUP(I30,负债!$A:$P,9,0)/100 -> 2272.36 | W30: =VLOOKUP(I30,负债!$A:$P,6,0)/100 -> 16567.47 | X30: =VLOOKUP(I30,负债!$A:$P,2,0)/100 -> 69701.95 | Y30: =T30-V30-W30 -> 51250.57
I31: 44020 | J31: =VLOOKUP(I31,资产!$A:$AF,8,0)/100 -> 42313.55 | K31: =VLOOKUP(I31,资产!$A:$AF,9,0)/100 -> 3260.44 | L31: =VLOOKUP(I31,资产!$A:$AF,10,0)/100 -> 35992.73 | M31: =(VLOOKUP(I31,资产!$A:$AF,13,0)+VLOOKUP(I31,资产!$A:$AF,14,0)+VLOOKUP(I31,资产!$A:$AF,15,0))/100 -> 9542.42 | N31: =VLOOKUP(I31,资产!$A:$AF,16,0)/100 -> 16072.39 | O31: =VLOOKUP(I31,资产!$A:$AF,17,0)/100 -> 7354.26 | P31: =VLOOKUP(I31,资产!$A:$AF,18,0)/100 -> 9344.48 | Q31: =VLOOKUP(I31,资产!$A:$AF,20,0)/100 -> 19114.01 | R31: =VLOOKUP(I31,负债!$A:$P,5,0)/100 -> 28132.96 | S31: =VLOOKUP(I31,负债!$A:$P,6,0)/100 -> 16244.04 | T31: =VLOOKUP(I31,资产!$A:$AF,2,0)/100 -> 69207.16 | U31: =VLOOKUP(I31,资产!$A:$AF,7,0)/100 -> 61451.03 | V31: =VLOOKUP(I31,负债!$A:$P,9,0)/100 -> 2248.6 | W31: =VLOOKUP(I31,负债!$A:$P,6,0)/100 -> 16244.04 | X31: =VLOOKUP(I31,负债!$A:$P,2,0)/100 -> 68819.55 | Y31: =T31-V31-W31 -> 50714.52
I32: 44027 | J32: =VLOOKUP(I32,资产!$A:$AF,8,0)/100 -> 42532.29 | K32: =VLOOKUP(I32,资产!$A:$AF,9,0)/100 -> 3260.44 | L32: =VLOOKUP(I32,资产!$A:$AF,10,0)/100 -> 36250.89 | M32: =(VLOOKUP(I32,资产!$A:$AF,13,0)+VLOOKUP(I32,资产!$A:$AF,14,0)+VLOOKUP(I32,资产!$A:$AF,15,0))/100 -> 9716.59 | N32: =VLOOKUP(I32,资产!$A:$AF,16,0)/100 -> 16048.39 | O32: =VLOOKUP(I32,资产!$A:$AF,17,0)/100 -> 7381.29 | P32: =VLOOKUP(I32,资产!$A:$AF,18,0)/100 -> 9386.04 | Q32: =VLOOKUP(I32,资产!$A:$AF,20,0)/100 -> 19483.88 | R32: =VLOOKUP(I32,负债!$A:$P,5,0)/100 -> 27326.49 | S32: =VLOOKUP(I32,负债!$A:$P,6,0)/100 -> 17404.55 | T32: =VLOOKUP(I32,资产!$A:$AF,2,0)/100 -> 69586.04 | U32: =VLOOKUP(I32,资产!$A:$AF,7,0)/100 -> 62039.65 | V32: =VLOOKUP(I32,负债!$A:$P,9,0)/100 -> 2242.29 | W32: =VLOOKUP(I32,负债!$A:$P,6,0)/100 -> 17404.55 | X32: =VLOOKUP(I32,负债!$A:$P,2,0)/100 -> 69198.43 | Y32: =T32-V32-W32 -> 49939.2
I33: 44034 | J33: =VLOOKUP(I33,资产!$A:$AF,8,0)/100 -> 42658.78 | K33: =VLOOKUP(I33,资产!$A:$AF,9,0)/100 -> 3260.44 | L33: =VLOOKUP(I33,资产!$A:$AF,10,0)/100 -> 36364.25 | M33: =(VLOOKUP(I33,资产!$A:$AF,13,0)+VLOOKUP(I33,资产!$A:$AF,14,0)+VLOOKUP(I33,资产!$A:$AF,15,0))/100 -> 9716.58 | N33: =VLOOKUP(I33,资产!$A:$AF,16,0)/100 -> 16071.35 | O33: =VLOOKUP(I33,资产!$A:$AF,17,0)/100 -> 7458.67 | P33: =VLOOKUP(I33,资产!$A:$AF,18,0)/100 -> 9412.19 | Q33: =VLOOKUP(I33,资产!$A:$AF,20,0)/100 -> 19706 | R33: =VLOOKUP(I33,负债!$A:$P,5,0)/100 -> 26596.58 | S33: =VLOOKUP(I33,负债!$A:$P,6,0)/100 -> 17771.8 | T33: =VLOOKUP(I33,资产!$A:$AF,2,0)/100 -> 69647.55 | U33: =VLOOKUP(I33,资产!$A:$AF,7,0)/100 -> 62388.25 | V33: =VLOOKUP(I33,负债!$A:$P,9,0)/100 -> 2146.65 | W33: =VLOOKUP(I33,负债!$A:$P,6,0)/100 -> 17771.8 | X33: =VLOOKUP(I33,负债!$A:$P,2,0)/100 -> 69259.94 | Y33: =T33-V33-W33 -> 49729.1
I34: 44041 | J34: =VLOOKUP(I34,资产!$A:$AF,8,0)/100 -> 42935.63 | K34: =VLOOKUP(I34,资产!$A:$AF,9,0)/100 -> 3260.44 | L34: =VLOOKUP(I34,资产!$A:$AF,10,0)/100 -> 36614.92 | M34: =(VLOOKUP(I34,资产!$A:$AF,13,0)+VLOOKUP(I34,资产!$A:$AF,14,0)+VLOOKUP(I34,资产!$A:$AF,15,0))/100 -> 9755.05 | N34: =VLOOKUP(I34,资产!$A:$AF,16,0)/100 -> 16272.18 | O34: =VLOOKUP(I34,资产!$A:$AF,17,0)/100 -> 7461.56 | P34: =VLOOKUP(I34,资产!$A:$AF,18,0)/100 -> 9446.84 | Q34: =VLOOKUP(I34,资产!$A:$AF,20,0)/100 -> 19333.8 | R34: =VLOOKUP(I34,负债!$A:$P,5,0)/100 -> 26853.76 | S34: =VLOOKUP(I34,负债!$A:$P,6,0)/100 -> 17924.34 | T34: =VLOOKUP(I34,资产!$A:$AF,2,0)/100 -> 69490.32 | U34: =VLOOKUP(I34,资产!$A:$AF,7,0)/100 -> 62292.91 | V34: =VLOOKUP(I34,负债!$A:$P,9,0)/100 -> 2170.53 | W34: =VLOOKUP(I34,负债!$A:$P,6,0)/100 -> 17924.34 | X34: =VLOOKUP(I34,负债!$A:$P,2,0)/100 -> 69102.41 | Y34: =T34-V34-W34 -> 49395.45
I35: 44048 | J35: =VLOOKUP(I35,资产!$A:$AF,8,0)/100 -> 43056.51 | K35: =VLOOKUP(I35,资产!$A:$AF,9,0)/100 -> 3260.44 | L35: =VLOOKUP(I35,资产!$A:$AF,10,0)/100 -> 36704.35 | M35: =(VLOOKUP(I35,资产!$A:$AF,13,0)+VLOOKUP(I35,资产!$A:$AF,14,0)+VLOOKUP(I35,资产!$A:$AF,15,0))/100 -> 9716.66 | N35: =VLOOKUP(I35,资产!$A:$AF,16,0)/100 -> 16392.44 | O35: =VLOOKUP(I35,资产!$A:$AF,17,0)/100 -> 7454.63 | P35: =VLOOKUP(I35,资产!$A:$AF,18,0)/100 -> 9492.8 | Q35: =VLOOKUP(I35,资产!$A:$AF,20,0)/100 -> 19334.66 | R35: =VLOOKUP(I35,负债!$A:$P,5,0)/100 -> 27535.31 | S35: =VLOOKUP(I35,负债!$A:$P,6,0)/100 -> 17066.37 | T35: =VLOOKUP(I35,资产!$A:$AF,2,0)/100 -> 69452.37 | U35: =VLOOKUP(I35,资产!$A:$AF,7,0)/100 -> 62414.64 | V35: =VLOOKUP(I35,负债!$A:$P,9,0)/100 -> 2124.48 | W35: =VLOOKUP(I35,负债!$A:$P,6,0)/100 -> 17066.37 | X35: =VLOOKUP(I35,负债!$A:$P,2,0)/100 -> 69063.62 | Y35: =T35-V35-W35 -> 50261.52
I36: 44055 | J36: =VLOOKUP(I36,资产!$A:$AF,8,0)/100 -> 43200.93 | K36: =VLOOKUP(I36,资产!$A:$AF,9,0)/100 -> 3260.44 | L36: =VLOOKUP(I36,资产!$A:$AF,10,0)/100 -> 36817.69 | M36: =(VLOOKUP(I36,资产!$A:$AF,13,0)+VLOOKUP(I36,资产!$A:$AF,14,0)+VLOOKUP(I36,资产!$A:$AF,15,0))/100 -> 9716.95 | N36: =VLOOKUP(I36,资产!$A:$AF,16,0)/100 -> 16425.29 | O36: =VLOOKUP(I36,资产!$A:$AF,17,0)/100 -> 7546.25 | P36: =VLOOKUP(I36,资产!$A:$AF,18,0)/100 -> 9512.44 | Q36: =VLOOKUP(I36,资产!$A:$AF,20,0)/100 -> 19335.48 | R36: =VLOOKUP(I36,负债!$A:$P,5,0)/100 -> 28281.7 | S36: =VLOOKUP(I36,负债!$A:$P,6,0)/100 -> 16351.43 | T36: =VLOOKUP(I36,资产!$A:$AF,2,0)/100 -> 69572.77 | U36: =VLOOKUP(I36,资产!$A:$AF,7,0)/100 -> 62559.88 | V36: =VLOOKUP(I36,负债!$A:$P,9,0)/100 -> 2183.46 | W36: =VLOOKUP(I36,负债!$A:$P,6,0)/100 -> 16351.43 | X36: =VLOOKUP(I36,负债!$A:$P,2,0)/100 -> 69183.91 | Y36: =T36-V36-W36 -> 51037.88
... I64: 44251 | J64: =VLOOKUP(I64,资产!$A:$AF,8,0)/100 -> 48445.74 | K64: =VLOOKUP(I64,资产!$A:$AF,9,0)/100 -> 3260.44 | L64: =VLOOKUP(I64,资产!$A:$AF,10,0)/100 -> 41507.79 | M64: =(VLOOKUP(I64,资产!$A:$AF,13,0)+VLOOKUP(I64,资产!$A:$AF,14,0)+VLOOKUP(I64,资产!$A:$AF,15,0))/100 -> 10622.71 | N64: =VLOOKUP(I64,资产!$A:$AF,16,0)/100 -> 18332.1 | O64: =VLOOKUP(I64,资产!$A:$AF,17,0)/100 -> 8587.15 | P64: =VLOOKUP(I64,资产!$A:$AF,18,0)/100 -> 10903.79 | Q64: =VLOOKUP(I64,资产!$A:$AF,20,0)/100 -> 21806.78 | R64: =VLOOKUP(I64,负债!$A:$P,5,0)/100 -> 33842.62 | S64: =VLOOKUP(I64,负债!$A:$P,6,0)/100 -> 14396.46 | T64: =VLOOKUP(I64,资产!$A:$AF,2,0)/100 -> 75901.11 | U64: =VLOOKUP(I64,资产!$A:$AF,7,0)/100 -> 70275.99 | V64: =VLOOKUP(I64,负债!$A:$P,9,0)/100 -> 2053.73 | W64: =VLOOKUP(I64,负债!$A:$P,6,0)/100 -> 14396.46 | X64: =VLOOKUP(I64,负债!$A:$P,2,0)/100 -> 75509.17 | Y64: =T64-V64-W64 -> 59450.92
A65: 0 | C65: 总资产 | D65: =VLOOKUP($C$1,资产!$A:$AF,2,0) -> 6713643 | F65: 总负债 | G65: =VLOOKUP($C$1,负债!$A:$P,2,0) -> 6666407 | I65: 44258 | J65: =VLOOKUP(I65,资产!$A:$AF,8,0)/100 -> 48672.79 | K65: =VLOOKUP(I65,资产!$A:$AF,9,0)/100 -> 3260.44 | L65: =VLOOKUP(I65,资产!$A:$AF,10,0)/100 -> 41706.5 | M65: =(VLOOKUP(I65,资产!$A:$AF,13,0)+VLOOKUP(I65,资产!$A:$AF,14,0)+VLOOKUP(I65,资产!$A:$AF,15,0))/100 -> 10459.04 | N65: =VLOOKUP(I65,资产!$A:$AF,16,0)/100 -> 18518.55 | O65: =VLOOKUP(I65,资产!$A:$AF,17,0)/100 -> 8666.24 | P65: =VLOOKUP(I65,资产!$A:$AF,18,0)/100 -> 11028.96 | Q65: =VLOOKUP(I65,资产!$A:$AF,20,0)/100 -> 21334 | R65: =VLOOKUP(I65,负债!$A:$P,5,0)/100 -> 35648.5 | S65: =VLOOKUP(I65,负债!$A:$P,6,0)/100 -> 14202.38 | T65: =VLOOKUP(I65,资产!$A:$AF,2,0)/100 -> 75575.24 | U65: =VLOOKUP(I65,资产!$A:$AF,7,0)/100 -> 70030.26 | V65: =VLOOKUP(I65,负债!$A:$P,9,0)/100 -> 2033.39 | W65: =VLOOKUP(I65,负债!$A:$P,6,0)/100 -> 14202.38 | X65: =VLOOKUP(I65,负债!$A:$P,2,0)/100 -> 75183.23 | Y65: =T65-V65-W65 -> 59339.47
A66: 1 | C66: * 黄金证券账户 | D66: =VLOOKUP($C$1,资产!$A:$AF,3,0) -> 11037 | F66: * 存款 | G66: =VLOOKUP($C$1,负债!$A:$P,3,0) -> 4144576 | I66: 44265 | J66: =VLOOKUP(I66,资产!$A:$AF,8,0)/100 -> 48890.07 | K66: =VLOOKUP(I66,资产!$A:$AF,9,0)/100 -> 3260.44 | L66: =VLOOKUP(I66,资产!$A:$AF,10,0)/100 -> 41907.87 | M66: =(VLOOKUP(I66,资产!$A:$AF,13,0)+VLOOKUP(I66,资产!$A:$AF,14,0)+VLOOKUP(I66,资产!$A:$AF,15,0))/100 -> 10459.32 | N66: =VLOOKUP(I66,资产!$A:$AF,16,0)/100 -> 18626.2 | O66: =VLOOKUP(I66,资产!$A:$AF,17,0)/100 -> 8709.02 | P66: =VLOOKUP(I66,资产!$A:$AF,18,0)/100 -> 11095.53 | Q66: =VLOOKUP(I66,资产!$A:$AF,20,0)/100 -> 21334.36 | R66: =VLOOKUP(I66,负债!$A:$P,5,0)/100 -> 36467.32 | S66: =VLOOKUP(I66,负债!$A:$P,6,0)/100 -> 13102.73 | T66: =VLOOKUP(I66,资产!$A:$AF,2,0)/100 -> 75799.01 | U66: =VLOOKUP(I66,资产!$A:$AF,7,0)/100 -> 70247.9 | V66: =VLOOKUP(I66,负债!$A:$P,9,0)/100 -> 1937.5 | W66: =VLOOKUP(I66,负债!$A:$P,6,0)/100 -> 13102.73 | X66: =VLOOKUP(I66,负债!$A:$P,2,0)/100 -> 75406.93 | Y66: =T66-V66-W66 -> 60758.78
A67: 1 | C67: * 特别提款权账户 | D67: =VLOOKUP($C$1,资产!$A:$AF,4,0) -> 15200 | F67: * 存款机构定期存款 | G67: =VLOOKUP($C$1,负债!$A:$P,4,0) -> 0 | I67: 44272 | J67: =VLOOKUP(I67,资产!$A:$AF,8,0)/100 -> 49116.33 | K67: =VLOOKUP(I67,资产!$A:$AF,9,0)/100 -> 3260.44 | L67: =VLOOKUP(I67,资产!$A:$AF,10,0)/100 -> 42130.56 | M67: =(VLOOKUP(I67,资产!$A:$AF,13,0)+VLOOKUP(I67,资产!$A:$AF,14,0)+VLOOKUP(I67,资产!$A:$AF,15,0))/100 -> 10551.15 | N67: =VLOOKUP(I67,资产!$A:$AF,16,0)/100 -> 18647.99 | O67: =VLOOKUP(I67,资产!$A:$AF,17,0)/100 -> 8771.15 | P67: =VLOOKUP(I67,资产!$A:$AF,18,0)/100 -> 11146.04 | Q67: =VLOOKUP(I67,资产!$A:$AF,20,0)/100 -> 22214.29 | R67: =VLOOKUP(I67,负债!$A:$P,5,0)/100 -> 38733.23 | S67: =VLOOKUP(I67,负债!$A:$P,6,0)/100 -> 10895.01 | T67: =VLOOKUP(I67,资产!$A:$AF,2,0)/100 -> 76935.06 | U67: =VLOOKUP(I67,资产!$A:$AF,7,0)/100 -> 71354.09 | V67: =VLOOKUP(I67,负债!$A:$P,9,0)/100 -> 2055.16 | W67: =VLOOKUP(I67,负债!$A:$P,6,0)/100 -> 10895.01 | X67: =VLOOKUP(I67,负债!$A:$P,2,0)/100 -> 76542.87 | Y67: =T67-V67-W67 -> 63984.89
A68: 1 | C68: * 硬币 | D68: =VLOOKUP($C$1,资产!$A:$AF,5,0) -> 1405 | F68: * 存款准备金 | G68: =VLOOKUP($C$1,负债!$A:$P,5,0) -> 3106716 | I68: 44279 | J68: =VLOOKUP(I68,资产!$A:$AF,8,0)/100 -> 49213.02 | K68: =VLOOKUP(I68,资产!$A:$AF,9,0)/100 -> 3260.44 | L68: =VLOOKUP(I68,资产!$A:$AF,10,0)/100 -> 42183.91 | M68: =(VLOOKUP(I68,资产!$A:$AF,13,0)+VLOOKUP(I68,资产!$A:$AF,14,0)+VLOOKUP(I68,资产!$A:$AF,15,0))/100 -> 10551.44 | N68: =VLOOKUP(I68,资产!$A:$AF,16,0)/100 -> 18669.98 | O68: =VLOOKUP(I68,资产!$A:$AF,17,0)/100 -> 8785.99 | P68: =VLOOKUP(I68,资产!$A:$AF,18,0)/100 -> 11205.62 | Q68: =VLOOKUP(I68,资产!$A:$AF,20,0)/100 -> 22348.07 | R68: =VLOOKUP(I68,负债!$A:$P,5,0)/100 -> 38091.39 | S68: =VLOOKUP(I68,负债!$A:$P,6,0)/100 -> 10319.08 | T68: =VLOOKUP(I68,资产!$A:$AF,2,0)/100 -> 77196.22 | U68: =VLOOKUP(I68,资产!$A:$AF,7,0)/100 -> 71584.56 | V68: =VLOOKUP(I68,负债!$A:$P,9,0)/100 -> 2344.44 | W68: =VLOOKUP(I68,负债!$A:$P,6,0)/100 -> 10319.08 | X68: =VLOOKUP(I68,负债!$A:$P,2,0)/100 -> 76804 | Y68: =T68-V68-W68 -> 64532.7
A69: 1 | C69: * 持有证券、未摊销证券溢价和折扣、回购协议和贷款 | D69: =VLOOKUP($C$1,资产!$A:$AF,6,0) -> 6634267 | F69: * 美国财政部一般账户(TGA) | G69: =VLOOKUP($C$1,负债!$A:$P,6,0) -> 781979 | I69: 44286 | J69: =VLOOKUP(I69,资产!$A:$AF,8,0)/100 -> 49422.77 | K69: =VLOOKUP(I69,资产!$A:$AF,9,0)/100 -> 3260.44 | L69: =VLOOKUP(I69,资产!$A:$AF,10,0)/100 -> 42353.93 | M69: =(VLOOKUP(I69,资产!$A:$AF,13,0)+VLOOKUP(I69,资产!$A:$AF,14,0)+VLOOKUP(I69,资产!$A:$AF,15,0))/100 -> 10444.12 | N69: =VLOOKUP(I69,资产!$A:$AF,16,0)/100 -> 18815.34 | O69: =VLOOKUP(I69,资产!$A:$AF,17,0)/100 -> 8890.19 | P69: =VLOOKUP(I69,资产!$A:$AF,18,0)/100 -> 11273.12 | Q69: =VLOOKUP(I69,资产!$A:$AF,20,0)/100 -> 21846.83 | R69: =VLOOKUP(I69,负债!$A:$P,5,0)/100 -> 36727.02 | S69: =VLOOKUP(I69,负债!$A:$P,6,0)/100 -> 11219.51 | T69: =VLOOKUP(I69,资产!$A:$AF,2,0)/100 -> 76889.88 | U69: =VLOOKUP(I69,资产!$A:$AF,7,0)/100 -> 71293.08 | V69: =VLOOKUP(I69,负债!$A:$P,9,0)/100 -> 3521.77 | W69: =VLOOKUP(I69,负债!$A:$P,6,0)/100 -> 11219.51 | X69: =VLOOKUP(I69,负债!$A:$P,2,0)/100 -> 76497.34 | Y69: =T69-V69-W69 -> 62148.6
A70: 2 | C70: * 持有证券 | D70: =VLOOKUP($C$1,资产!$A:$AF,7,0) -> 6437719 | F70: * 外国官方 | G70: =VLOOKUP($C$1,负债!$A:$P,7,0) -> 9443 | I70: 44293 | J70: =VLOOKUP(I70,资产!$A:$AF,8,0)/100 -> 49590.33 | K70: =VLOOKUP(I70,资产!$A:$AF,9,0)/100 -> 3260.44 | L70: =VLOOKUP(I70,资产!$A:$AF,10,0)/100 -> 42516.62 | M70: =(VLOOKUP(I70,资产!$A:$AF,13,0)+VLOOKUP(I70,资产!$A:$AF,14,0)+VLOOKUP(I70,资产!$A:$AF,15,0))/100 -> 10502.55 | N70: =VLOOKUP(I70,资产!$A:$AF,16,0)/100 -> 18886.84 | O70: =VLOOKUP(I70,资产!$A:$AF,17,0)/100 -> 8891.86 | P70: =VLOOKUP(I70,资产!$A:$AF,18,0)/100 -> 11309.08 | Q70: =VLOOKUP(I70,资产!$A:$AF,20,0)/100 -> 21846.84 | R70: =VLOOKUP(I70,负债!$A:$P,5,0)/100 -> 39440.55 | S70: =VLOOKUP(I70,负债!$A:$P,6,0)/100 -> 9549.68 | T70: =VLOOKUP(I70,资产!$A:$AF,2,0)/100 -> 77088.82 | U70: =VLOOKUP(I70,资产!$A:$AF,7,0)/100 -> 71460.64 | V70: =VLOOKUP(I70,负债!$A:$P,9,0)/100 -> 2720.73 | W70: =VLOOKUP(I70,负债!$A:$P,6,0)/100 -> 9549.68 | X70: =VLOOKUP(I70,负债!$A:$P,2,0)/100 -> 76696.16 | Y70: =T70-V70-W70 -> 64818.41
A71: 3 | C71: * 美国国债 | D71: =VLOOKUP($C$1,资产!$A:$AF,8,0) -> 4457712 | F71: * 其他存款 | G71: =VLOOKUP($C$1,负债!$A:$P,8,0) -> 246438 | I71: 44300 | J71: =VLOOKUP(I71,资产!$A:$AF,8,0)/100 -> 49734.99 | K71: =VLOOKUP(I71,资产!$A:$AF,9,0)/100 -> 3260.44 | L71: =VLOOKUP(I71,资产!$A:$AF,10,0)/100 -> 42629.99 | M71: =(VLOOKUP(I71,资产!$A:$AF,13,0)+VLOOKUP(I71,资产!$A:$AF,14,0)+VLOOKUP(I71,资产!$A:$AF,15,0))/100 -> 10502.93 | N71: =VLOOKUP(I71,资产!$A:$AF,16,0)/100 -> 18926.26 | O71: =VLOOKUP(I71,资产!$A:$AF,17,0)/100 -> 8942.08 | P71: =VLOOKUP(I71,资产!$A:$AF,18,0)/100 -> 11363.72 | Q71: =VLOOKUP(I71,资产!$A:$AF,20,0)/100 -> 22490.19 | R71: =VLOOKUP(I71,负债!$A:$P,5,0)/100 -> 39364.54 | S71: =VLOOKUP(I71,负债!$A:$P,6,0)/100 -> 9216.85 | T71: =VLOOKUP(I71,资产!$A:$AF,2,0)/100 -> 77931.04 | U71: =VLOOKUP(I71,资产!$A:$AF,7,0)/100 -> 72248.65 | V71: =VLOOKUP(I71,负债!$A:$P,9,0)/100 -> 2818.53 | W71: =VLOOKUP(I71,负债!$A:$P,6,0)/100 -> 9216.85 | X71: =VLOOKUP(I71,负债!$A:$P,2,0)/100 -> 77538.36 | Y71: =T71-V71-W71 -> 65895.66
A72: 4 | C72: * 短期债券 | D72: =VLOOKUP($C$1,资产!$A:$AF,9,0) -> 459607 | F72: * 逆向回购协议 | G72: =VLOOKUP($C$1,负债!$A:$P,9,0) -> 342628 | I72: 44307 | J72: =VLOOKUP(I72,资产!$A:$AF,8,0)/100 -> 50003.06 | K72: =VLOOKUP(I72,资产!$A:$AF,9,0)/100 -> 3260.44 | L72: =VLOOKUP(I72,资产!$A:$AF,10,0)/100 -> 42970.74 | M72: =(VLOOKUP(I72,资产!$A:$AF,13,0)+VLOOKUP(I72,资产!$A:$AF,14,0)+VLOOKUP(I72,资产!$A:$AF,15,0))/100 -> 10561.57 | N72: =VLOOKUP(I72,资产!$A:$AF,16,0)/100 -> 18990.3 | O72: =VLOOKUP(I72,资产!$A:$AF,17,0)/100 -> 9006.97 | P72: =VLOOKUP(I72,资产!$A:$AF,18,0)/100 -> 11444.23 | Q72: =VLOOKUP(I72,资产!$A:$AF,20,0)/100 -> 22469.89 | R72: =VLOOKUP(I72,负债!$A:$P,5,0)/100 -> 37674.54 | S72: =VLOOKUP(I72,负债!$A:$P,6,0)/100 -> 10034.43 | T72: =VLOOKUP(I72,资产!$A:$AF,2,0)/100 -> 78209.48 | U72: =VLOOKUP(I72,资产!$A:$AF,7,0)/100 -> 72496.42 | V72: =VLOOKUP(I72,负债!$A:$P,9,0)/100 -> 3027.9 | W72: =VLOOKUP(I72,负债!$A:$P,6,0)/100 -> 10034.43 | X72: =VLOOKUP(I72,负债!$A:$P,2,0)/100 -> 77816.79 | Y72: =T72-V72-W72 -> 65147.15
A73: 4 | C73: * 中长期名义债券 | D73: =VLOOKUP($C$1,资产!$A:$AF,10,0) -> 3615393 | F73: * 联储票据(扣除美联储自持部分) | G73: =VLOOKUP($C$1,负债!$A:$P,10,0) -> 2410379 | I73: 44314 | J73: =VLOOKUP(I73,资产!$A:$AF,8,0)/100 -> 50147.62 | K73: =VLOOKUP(I73,资产!$A:$AF,9,0)/100 -> 3260.44 | L73: =VLOOKUP(I73,资产!$A:$AF,10,0)/100 -> 43084.11 | M73: =(VLOOKUP(I73,资产!$A:$AF,13,0)+VLOOKUP(I73,资产!$A:$AF,14,0)+VLOOKUP(I73,资产!$A:$AF,15,0))/100 -> 10561.97 | N73: =VLOOKUP(I73,资产!$A:$AF,16,0)/100 -> 19026.33 | O73: =VLOOKUP(I73,资产!$A:$AF,17,0)/100 -> 9060.47 | P73: =VLOOKUP(I73,资产!$A:$AF,18,0)/100 -> 11498.86 | Q73: =VLOOKUP(I73,资产!$A:$AF,20,0)/100 -> 21913.05 | R73: =VLOOKUP(I73,负债!$A:$P,5,0)/100 -> 38890.18 | S73: =VLOOKUP(I73,负债!$A:$P,6,0)/100 -> 9322.87 | T73: =VLOOKUP(I73,资产!$A:$AF,2,0)/100 -> 77809.62 | U73: =VLOOKUP(I73,资产!$A:$AF,7,0)/100 -> 72084.14 | V73: =VLOOKUP(I73,负债!$A:$P,9,0)/100 -> 3828.91 | W73: =VLOOKUP(I73,负债!$A:$P,6,0)/100 -> 9322.87 | X73: =VLOOKUP(I73,负债!$A:$P,2,0)/100 -> 77416.93 | Y73: =T73-V73-W73 -> 64657.84
A74: 4 | C74: * 中长期通胀指数债券 | D74: =VLOOKUP($C$1,资产!$A:$AF,11,0) -> 279041 | F74: * 延迟入账现金项目 | G74: =VLOOKUP($C$1,负债!$A:$P,11,0) -> 316 | I74: 44321 | J74: =VLOOKUP(I74,资产!$A:$AF,8,0)/100 -> 50404.18 | K74: =VLOOKUP(I74,资产!$A:$AF,9,0)/100 -> 3260.44 | L74: =VLOOKUP(I74,资产!$A:$AF,10,0)/100 -> 43300.43 | M74: =(VLOOKUP(I74,资产!$A:$AF,13,0)+VLOOKUP(I74,资产!$A:$AF,14,0)+VLOOKUP(I74,资产!$A:$AF,15,0))/100 -> 10334.17 | N74: =VLOOKUP(I74,资产!$A:$AF,16,0)/100 -> 19426.74 | O74: =VLOOKUP(I74,资产!$A:$AF,17,0)/100 -> 9062.38 | P74: =VLOOKUP(I74,资产!$A:$AF,18,0)/100 -> 11580.9 | Q74: =VLOOKUP(I74,资产!$A:$AF,20,0)/100 -> 21913.25 | R74: =VLOOKUP(I74,负债!$A:$P,5,0)/100 -> 39008.03 | S74: =VLOOKUP(I74,负债!$A:$P,6,0)/100 -> 9461.34 | T74: =VLOOKUP(I74,资产!$A:$AF,2,0)/100 -> 78104.86 | U74: =VLOOKUP(I74,资产!$A:$AF,7,0)/100 -> 72340.9 | V74: =VLOOKUP(I74,负债!$A:$P,9,0)/100 -> 3883.04 | W74: =VLOOKUP(I74,负债!$A:$P,6,0)/100 -> 9461.34 | X74: =VLOOKUP(I74,负债!$A:$P,2,0)/100 -> 77712.13 | Y74: =T74-V74-W74 -> 64760.48
A75: 4 | C75: * 通胀补偿 | D75: =VLOOKUP($C$1,资产!$A:$AF,12,0) -> 103670 | F75: * 财政部对信贷部门的捐助 | G75: =VLOOKUP($C$1,负债!$A:$P,12,0) -> 821 | I75: 44328 | J75: =VLOOKUP(I75,资产!$A:$AF,8,0)/100 -> 50543.95 | K75: =VLOOKUP(I75,资产!$A:$AF,9,0)/100 -> 3260.44 | L75: =VLOOKUP(I75,资产!$A:$AF,10,0)/100 -> 43396.45 | M75: =(VLOOKUP(I75,资产!$A:$AF,13,0)+VLOOKUP(I75,资产!$A:$AF,14,0)+VLOOKUP(I75,资产!$A:$AF,15,0))/100 -> 10334.66 | N75: =VLOOKUP(I75,资产!$A:$AF,16,0)/100 -> 19480.27 | O75: =VLOOKUP(I75,资产!$A:$AF,17,0)/100 -> 9109.43 | P75: =VLOOKUP(I75,资产!$A:$AF,18,0)/100 -> 11619.58 | Q75: =VLOOKUP(I75,资产!$A:$AF,20,0)/100 -> 21913.25 | R75: =VLOOKUP(I75,负债!$A:$P,5,0)/100 -> 39558.64 | S75: =VLOOKUP(I75,负债!$A:$P,6,0)/100 -> 8642.53 | T75: =VLOOKUP(I75,资产!$A:$AF,2,0)/100 -> 78306.63 | U75: =VLOOKUP(I75,资产!$A:$AF,7,0)/100 -> 72480.67 | V75: =VLOOKUP(I75,负债!$A:$P,9,0)/100 -> 4288.32 | W75: =VLOOKUP(I75,负债!$A:$P,6,0)/100 -> 8642.53 | X75: =VLOOKUP(I75,负债!$A:$P,2,0)/100 -> 77912.72 | Y75: =T75-V75-W75 -> 65375.78
A76: 4 | C76: * 15天以内 | D76: =VLOOKUP($C$1,资产!$A:$AF,13,0) -> 88919 | F76: * 其他负债及应计股息 | G76: =VLOOKUP($C$1,负债!$A:$P,13,0) -> -232314 | I76: 44335 | J76: =VLOOKUP(I76,资产!$A:$AF,8,0)/100 -> 50718.21 | K76: =VLOOKUP(I76,资产!$A:$AF,9,0)/100 -> 3260.44 | L76: =VLOOKUP(I76,资产!$A:$AF,10,0)/100 -> 43551.82 | M76: =(VLOOKUP(I76,资产!$A:$AF,13,0)+VLOOKUP(I76,资产!$A:$AF,14,0)+VLOOKUP(I76,资产!$A:$AF,15,0))/100 -> 10395.89 | N76: =VLOOKUP(I76,资产!$A:$AF,16,0)/100 -> 19332.83 | O76: =VLOOKUP(I76,资产!$A:$AF,17,0)/100 -> 9189.38 | P76: =VLOOKUP(I76,资产!$A:$AF,18,0)/100 -> 11800.11 | Q76: =VLOOKUP(I76,资产!$A:$AF,20,0)/100 -> 22775.61 | R76: =VLOOKUP(I76,负债!$A:$P,5,0)/100 -> 38239.81 | S76: =VLOOKUP(I76,负债!$A:$P,6,0)/100 -> 8608.33 | T76: =VLOOKUP(I76,资产!$A:$AF,2,0)/100 -> 79228.83 | U76: =VLOOKUP(I76,资产!$A:$AF,7,0)/100 -> 73517.29 | V76: =VLOOKUP(I76,负债!$A:$P,9,0)/100 -> 5221.56 | W76: =VLOOKUP(I76,负债!$A:$P,6,0)/100 -> 8608.33 | X76: =VLOOKUP(I76,负债!$A:$P,2,0)/100 -> 78834.62 | Y76: =T76-V76-W76 -> 65398.94
A77: 4 | C77: * 16-90天 | D77: =VLOOKUP($C$1,资产!$A:$AF,14,0) -> 343911 | I77: 44342 | J77: =VLOOKUP(I77,资产!$A:$AF,8,0)/100 -> 50871.57 | K77: =VLOOKUP(I77,资产!$A:$AF,9,0)/100 -> 3260.44 | L77: =VLOOKUP(I77,资产!$A:$AF,10,0)/100 -> 43677.86 | M77: =(VLOOKUP(I77,资产!$A:$AF,13,0)+VLOOKUP(I77,资产!$A:$AF,14,0)+VLOOKUP(I77,资产!$A:$AF,15,0))/100 -> 10396.4 | N77: =VLOOKUP(I77,资产!$A:$AF,16,0)/100 -> 19373.8 | O77: =VLOOKUP(I77,资产!$A:$AF,17,0)/100 -> 9265.62 | P77: =VLOOKUP(I77,资产!$A:$AF,18,0)/100 -> 11835.76 | Q77: =VLOOKUP(I77,资产!$A:$AF,20,0)/100 -> 22442.65 | R77: =VLOOKUP(I77,负债!$A:$P,5,0)/100 -> 38516.23 | S77: =VLOOKUP(I77,负债!$A:$P,6,0)/100 -> 7789.12 | T77: =VLOOKUP(I77,资产!$A:$AF,2,0)/100 -> 79035.41 | U77: =VLOOKUP(I77,资产!$A:$AF,7,0)/100 -> 73337.69 | V77: =VLOOKUP(I77,负债!$A:$P,9,0)/100 -> 6704.33 | W77: =VLOOKUP(I77,负债!$A:$P,6,0)/100 -> 7789.12 | X77: =VLOOKUP(I77,负债!$A:$P,2,0)/100 -> 78640.34 | Y77: =T77-V77-W77 -> 64541.96
A78: 4 | C78: * 91天-1年 | D78: =VLOOKUP($C$1,资产!$A:$AF,15,0) -> 504852 | F78: 全部资本（净资产） | G78: =VLOOKUP($C$1,负债!$A:$Q,17,0) -> 47236 | I78: 44349 | J78: =VLOOKUP(I78,资产!$A:$AF,8,0)/100 -> 51190.23 | K78: =VLOOKUP(I78,资产!$A:$AF,9,0)/100 -> 3260.44 | L78: =VLOOKUP(I78,资产!$A:$AF,10,0)/100 -> 43989.9 | M78: =(VLOOKUP(I78,资产!$A:$AF,13,0)+VLOOKUP(I78,资产!$A:$AF,14,0)+VLOOKUP(I78,资产!$A:$AF,15,0))/100 -> 10224.73 | N78: =VLOOKUP(I78,资产!$A:$AF,16,0)/100 -> 19768.06 | O78: =VLOOKUP(I78,资产!$A:$AF,17,0)/100 -> 9287.55 | P78: =VLOOKUP(I78,资产!$A:$AF,18,0)/100 -> 11909.91 | Q78: =VLOOKUP(I78,资产!$A:$AF,20,0)/100 -> 22442.7 | R78: =VLOOKUP(I78,负债!$A:$P,5,0)/100 -> 38482.62 | S78: =VLOOKUP(I78,负债!$A:$P,6,0)/100 -> 8120.87 | T78: =VLOOKUP(I78,资产!$A:$AF,2,0)/100 -> 79357.03 | U78: =VLOOKUP(I78,资产!$A:$AF,7,0)/100 -> 73656.41 | V78: =VLOOKUP(I78,负债!$A:$P,9,0)/100 -> 6729.06 | W78: =VLOOKUP(I78,负债!$A:$P,6,0)/100 -> 8120.87 | X78: =VLOOKUP(I78,负债!$A:$P,2,0)/100 -> 78961.95 | Y78: =T78-V78-W78 -> 64507.1
A79: 4 | C79: * 1-5年 | D79: =VLOOKUP($C$1,资产!$A:$AF,16,0) -> 1429880 | F79: * 实缴资本 | G79: =VLOOKUP($C$1,负债!$A:$P,14,0) -> 40451 | I79: 44356 | J79: =VLOOKUP(I79,资产!$A:$AF,8,0)/100 -> 51298.91 | K79: =VLOOKUP(I79,资产!$A:$AF,9,0)/100 -> 3260.44 | L79: =VLOOKUP(I79,资产!$A:$AF,10,0)/100 -> 44055.68 | M79: =(VLOOKUP(I79,资产!$A:$AF,13,0)+VLOOKUP(I79,资产!$A:$AF,14,0)+VLOOKUP(I79,资产!$A:$AF,15,0))/100 -> 10225.32 | N79: =VLOOKUP(I79,资产!$A:$AF,16,0)/100 -> 19786.48 | O79: =VLOOKUP(I79,资产!$A:$AF,17,0)/100 -> 9339.34 | P79: =VLOOKUP(I79,资产!$A:$AF,18,0)/100 -> 11947.77 | Q79: =VLOOKUP(I79,资产!$A:$AF,20,0)/100 -> 22442.7 | R79: =VLOOKUP(I79,负债!$A:$P,5,0)/100 -> 39167.25 | S79: =VLOOKUP(I79,负债!$A:$P,6,0)/100 -> 6735.55 | T79: =VLOOKUP(I79,资产!$A:$AF,2,0)/100 -> 79523.27 | U79: =VLOOKUP(I79,资产!$A:$AF,7,0)/100 -> 73765.08 | V79: =VLOOKUP(I79,负债!$A:$P,9,0)/100 -> 7209.36 | W79: =VLOOKUP(I79,负债!$A:$P,6,0)/100 -> 6735.55 | X79: =VLOOKUP(I79,负债!$A:$P,2,0)/100 -> 79128.15 | Y79: =T79-V79-W79 -> 65578.36
A80: 4 | C80: * 5-10年 | D80: =VLOOKUP($C$1,资产!$A:$AF,17,0) -> 481258 | F80: * 结余 | G80: =VLOOKUP($C$1,负债!$A:$P,15,0) -> 6785 | I80: 44363 | J80: =VLOOKUP(I80,资产!$A:$AF,8,0)/100 -> 51537.71 | K80: =VLOOKUP(I80,资产!$A:$AF,9,0)/100 -> 3260.44 | L80: =VLOOKUP(I80,资产!$A:$AF,10,0)/100 -> 44273.72 | M80: =(VLOOKUP(I80,资产!$A:$AF,13,0)+VLOOKUP(I80,资产!$A:$AF,14,0)+VLOOKUP(I80,资产!$A:$AF,15,0))/100 -> 10276.64 | N80: =VLOOKUP(I80,资产!$A:$AF,16,0)/100 -> 19820.4 | O80: =VLOOKUP(I80,资产!$A:$AF,17,0)/100 -> 9432.49 | P80: =VLOOKUP(I80,资产!$A:$AF,18,0)/100 -> 12008.19 | Q80: =VLOOKUP(I80,资产!$A:$AF,20,0)/100 -> 23281.24 | R80: =VLOOKUP(I80,负债!$A:$P,5,0)/100 -> 39057.36 | S80: =VLOOKUP(I80,负债!$A:$P,6,0)/100 -> 7651.14 | T80: =VLOOKUP(I80,资产!$A:$AF,2,0)/100 -> 80642.57 | U80: =VLOOKUP(I80,资产!$A:$AF,7,0)/100 -> 74842.42 | V80: =VLOOKUP(I80,负债!$A:$P,9,0)/100 -> 7437.6 | W80: =VLOOKUP(I80,负债!$A:$P,6,0)/100 -> 7651.14 | X80: =VLOOKUP(I80,负债!$A:$P,2,0)/100 -> 80246.54 | Y80: =T80-V80-W80 -> 65553.83
A81: 4 | C81: * 大于10年 | D81: =VLOOKUP($C$1,资产!$A:$AF,18,0) -> 1608892 | F81: * 其他资本账户 | G81: =VLOOKUP($C$1,负债!$A:$P,16,0) -> 0 | I81: 44370 | J81: =VLOOKUP(I81,资产!$A:$AF,8,0)/100 -> 51634.45 | K81: =VLOOKUP(I81,资产!$A:$AF,9,0)/100 -> 3260.44 | L81: =VLOOKUP(I81,资产!$A:$AF,10,0)/100 -> 44339.73 | M81: =(VLOOKUP(I81,资产!$A:$AF,13,0)+VLOOKUP(I81,资产!$A:$AF,14,0)+VLOOKUP(I81,资产!$A:$AF,15,0))/100 -> 10277.24 | N81: =VLOOKUP(I81,资产!$A:$AF,16,0)/100 -> 19837.09 | O81: =VLOOKUP(I81,资产!$A:$AF,17,0)/100 -> 9475.93 | P81: =VLOOKUP(I81,资产!$A:$AF,18,0)/100 -> 12044.18 | Q81: =VLOOKUP(I81,资产!$A:$AF,20,0)/100 -> 23541.55 | R81: =VLOOKUP(I81,负债!$A:$P,5,0)/100 -> 37657.14 | S81: =VLOOKUP(I81,负债!$A:$P,6,0)/100 -> 7338.77 | T81: =VLOOKUP(I81,资产!$A:$AF,2,0)/100 -> 81019.45 | U81: =VLOOKUP(I81,资产!$A:$AF,7,0)/100 -> 75199.47 | V81: =VLOOKUP(I81,负债!$A:$P,9,0)/100 -> 10559.31 | W81: =VLOOKUP(I81,负债!$A:$P,6,0)/100 -> 7338.77 | X81: =VLOOKUP(I81,负债!$A:$P,2,0)/100 -> 80623.41 | Y81: =T81-V81-W81 -> 63121.37
A82: 3 | C82: * 联邦机构债券 | D82: =VLOOKUP($C$1,资产!$A:$AF,19,0) -> 2347 | I82: 44377 | J82: =VLOOKUP(I82,资产!$A:$AF,8,0)/100 -> 51833.85 | K82: =VLOOKUP(I82,资产!$A:$AF,9,0)/100 -> 3260.44 | L82: =VLOOKUP(I82,资产!$A:$AF,10,0)/100 -> 44493.49 | M82: =(VLOOKUP(I82,资产!$A:$AF,13,0)+VLOOKUP(I82,资产!$A:$AF,14,0)+VLOOKUP(I82,资产!$A:$AF,15,0))/100 -> 10246.35 | N82: =VLOOKUP(I82,资产!$A:$AF,16,0)/100 -> 19957.09 | O82: =VLOOKUP(I82,资产!$A:$AF,17,0)/100 -> 9509.72 | P82: =VLOOKUP(I82,资产!$A:$AF,18,0)/100 -> 12120.68 | Q82: =VLOOKUP(I82,资产!$A:$AF,20,0)/100 -> 23196.37 | R82: =VLOOKUP(I82,负债!$A:$P,5,0)/100 -> 35116.3 | S82: =VLOOKUP(I82,负债!$A:$P,6,0)/100 -> 8519.29 | T82: =VLOOKUP(I82,资产!$A:$AF,2,0)/100 -> 80785.44 | U82: =VLOOKUP(I82,资产!$A:$AF,7,0)/100 -> 75053.69 | V82: =VLOOKUP(I82,负债!$A:$P,9,0)/100 -> 12609.25 | W82: =VLOOKUP(I82,负债!$A:$P,6,0)/100 -> 8519.29 | X82: =VLOOKUP(I82,负债!$A:$P,2,0)/100 -> 80389.4 | Y82: =T82-V82-W82 -> 59656.9
A83: 3 | C83: * 抵押贷款支持债券(MBS) | D83: =VLOOKUP($C$1,资产!$A:$AF,20,0) -> 1977661 | I83: 44384 | J83: =VLOOKUP(I83,资产!$A:$AF,8,0)/100 -> 52017.25 | K83: =VLOOKUP(I83,资产!$A:$AF,9,0)/100 -> 3260.44 | L83: =VLOOKUP(I83,资产!$A:$AF,10,0)/100 -> 44669.5 | M83: =(VLOOKUP(I83,资产!$A:$AF,13,0)+VLOOKUP(I83,资产!$A:$AF,14,0)+VLOOKUP(I83,资产!$A:$AF,15,0))/100 -> 10305.13 | N83: =VLOOKUP(I83,资产!$A:$AF,16,0)/100 -> 20025.23 | O83: =VLOOKUP(I83,资产!$A:$AF,17,0)/100 -> 9544.33 | P83: =VLOOKUP(I83,资产!$A:$AF,18,0)/100 -> 12142.56 | Q83: =VLOOKUP(I83,资产!$A:$AF,20,0)/100 -> 23196.37 | R83: =VLOOKUP(I83,负债!$A:$P,5,0)/100 -> 38562.03 | S83: =VLOOKUP(I83,负债!$A:$P,6,0)/100 -> 7248.98 | T83: =VLOOKUP(I83,资产!$A:$AF,2,0)/100 -> 80977.73 | U83: =VLOOKUP(I83,资产!$A:$AF,7,0)/100 -> 75237.09 | V83: =VLOOKUP(I83,负债!$A:$P,9,0)/100 -> 10493.32 | W83: =VLOOKUP(I83,负债!$A:$P,6,0)/100 -> 7248.98 | X83: =VLOOKUP(I83,负债!$A:$P,2,0)/100 -> 80581.7 | Y83: =T83-V83-W83 -> 63235.43
A84: 2 | C84: * 当前持有的未摊销证券溢价 | D84: =VLOOKUP($C$1,资产!$A:$AF,21,0) -> 216518 | I84: 44391 | J84: =VLOOKUP(I84,资产!$A:$AF,8,0)/100 -> 52225.7 | K84: =VLOOKUP(I84,资产!$A:$AF,9,0)/100 -> 3260.44 | L84: =VLOOKUP(I84,资产!$A:$AF,10,0)/100 -> 44847.52 | M84: =(VLOOKUP(I84,资产!$A:$AF,13,0)+VLOOKUP(I84,资产!$A:$AF,14,0)+VLOOKUP(I84,资产!$A:$AF,15,0))/100 -> 10305.69 | N84: =VLOOKUP(I84,资产!$A:$AF,16,0)/100 -> 20255.19 | O84: =VLOOKUP(I84,资产!$A:$AF,17,0)/100 -> 9486.34 | P84: =VLOOKUP(I84,资产!$A:$AF,18,0)/100 -> 12178.47 | Q84: =VLOOKUP(I84,资产!$A:$AF,20,0)/100 -> 24023.62 | R84: =VLOOKUP(I84,负债!$A:$P,5,0)/100 -> 39447 | S84: =VLOOKUP(I84,负债!$A:$P,6,0)/100 -> 6575.42 | T84: =VLOOKUP(I84,资产!$A:$AF,2,0)/100 -> 82016.51 | U84: =VLOOKUP(I84,资产!$A:$AF,7,0)/100 -> 76272.78 | V84: =VLOOKUP(I84,负债!$A:$P,9,0)/100 -> 11109.67 | W84: =VLOOKUP(I84,负债!$A:$P,6,0)/100 -> 6575.42 | X84: =VLOOKUP(I84,负债!$A:$P,2,0)/100 -> 81620.47 | Y84: =T84-V84-W84 -> 64331.42
A85: 2 | C85: * 当前持有的未摊销证券折扣 | D85: =VLOOKUP($C$1,资产!$A:$AF,22,0) -> -25615 | I85: 44398 | J85: =VLOOKUP(I85,资产!$A:$AF,8,0)/100 -> 52429.87 | K85: =VLOOKUP(I85,资产!$A:$AF,9,0)/100 -> 3260.44 | L85: =VLOOKUP(I85,资产!$A:$AF,10,0)/100 -> 45140.27 | M85: =(VLOOKUP(I85,资产!$A:$AF,13,0)+VLOOKUP(I85,资产!$A:$AF,14,0)+VLOOKUP(I85,资产!$A:$AF,15,0))/100 -> 10382.07 | N85: =VLOOKUP(I85,资产!$A:$AF,16,0)/100 -> 20203.68 | O85: =VLOOKUP(I85,资产!$A:$AF,17,0)/100 -> 9594.14 | P85: =VLOOKUP(I85,资产!$A:$AF,18,0)/100 -> 12249.98 | Q85: =VLOOKUP(I85,资产!$A:$AF,20,0)/100 -> 24221.77 | R85: =VLOOKUP(I85,负债!$A:$P,5,0)/100 -> 39745.47 | S85: =VLOOKUP(I85,负债!$A:$P,6,0)/100 -> 6162.94 | T85: =VLOOKUP(I85,资产!$A:$AF,2,0)/100 -> 82405.3 | U85: =VLOOKUP(I85,资产!$A:$AF,7,0)/100 -> 76675.1 | V85: =VLOOKUP(I85,负债!$A:$P,9,0)/100 -> 11368.78 | W85: =VLOOKUP(I85,负债!$A:$P,6,0)/100 -> 6162.94 | X85: =VLOOKUP(I85,负债!$A:$P,2,0)/100 -> 82009.24 | Y85: =T85-V85-W85 -> 64873.58
A86: 2 | C86: * 正向回购协议 | D86: =VLOOKUP($C$1,资产!$A:$AF,23,0) -> 7 | I86: 44405 | J86: =VLOOKUP(I86,资产!$A:$AF,8,0)/100 -> 52637.4 | K86: =VLOOKUP(I86,资产!$A:$AF,9,0)/100 -> 3260.44 | L86: =VLOOKUP(I86,资产!$A:$AF,10,0)/100 -> 45318.31 | M86: =(VLOOKUP(I86,资产!$A:$AF,13,0)+VLOOKUP(I86,资产!$A:$AF,14,0)+VLOOKUP(I86,资产!$A:$AF,15,0))/100 -> 10382.65 | N86: =VLOOKUP(I86,资产!$A:$AF,16,0)/100 -> 20347.25 | O86: =VLOOKUP(I86,资产!$A:$AF,17,0)/100 -> 9621.61 | P86: =VLOOKUP(I86,资产!$A:$AF,18,0)/100 -> 12285.89 | Q86: =VLOOKUP(I86,资产!$A:$AF,20,0)/100 -> 23847.79 | R86: =VLOOKUP(I86,负债!$A:$P,5,0)/100 -> 40010.61 | S86: =VLOOKUP(I86,负债!$A:$P,6,0)/100 -> 5369.66 | T86: =VLOOKUP(I86,资产!$A:$AF,2,0)/100 -> 82214.73 | U86: =VLOOKUP(I86,资产!$A:$AF,7,0)/100 -> 76508.66 | V86: =VLOOKUP(I86,负债!$A:$P,9,0)/100 -> 12201.33 | W86: =VLOOKUP(I86,负债!$A:$P,6,0)/100 -> 5369.66 | X86: =VLOOKUP(I86,负债!$A:$P,2,0)/100 -> 81818.75 | Y86: =T86-V86-W86 -> 64643.74
A87: 2 | C87: * 其他贷款 | D87: =VLOOKUP($C$1,资产!$A:$AF,24,0) -> 5637 | I87: 44412 | J87: =VLOOKUP(I87,资产!$A:$AF,8,0)/100 -> 52776.35 | K87: =VLOOKUP(I87,资产!$A:$AF,9,0)/100 -> 3260.44 | L87: =VLOOKUP(I87,资产!$A:$AF,10,0)/100 -> 45436.34 | M87: =(VLOOKUP(I87,资产!$A:$AF,13,0)+VLOOKUP(I87,资产!$A:$AF,14,0)+VLOOKUP(I87,资产!$A:$AF,15,0))/100 -> 10438.78 | N87: =VLOOKUP(I87,资产!$A:$AF,16,0)/100 -> 20382.69 | O87: =VLOOKUP(I87,资产!$A:$AF,17,0)/100 -> 9600.16 | P87: =VLOOKUP(I87,资产!$A:$AF,18,0)/100 -> 12354.72 | Q87: =VLOOKUP(I87,资产!$A:$AF,20,0)/100 -> 23847.85 | R87: =VLOOKUP(I87,负债!$A:$P,5,0)/100 -> 40458.93 | S87: =VLOOKUP(I87,负债!$A:$P,6,0)/100 -> 5058.71 | T87: =VLOOKUP(I87,资产!$A:$AF,2,0)/100 -> 82350.73 | U87: =VLOOKUP(I87,资产!$A:$AF,7,0)/100 -> 76647.67 | V87: =VLOOKUP(I87,负债!$A:$P,9,0)/100 -> 12163.57 | W87: =VLOOKUP(I87,负债!$A:$P,6,0)/100 -> 5058.71 | X87: =VLOOKUP(I87,负债!$A:$P,2,0)/100 -> 81953.76 | Y87: =T87-V87-W87 -> 65128.45
A88: 1 | C88: * MS Facilities LLC的净投资组合持有量(中产阶级贷款计划) | D88: =VLOOKUP($C$1,资产!$A:$AF,25,0) -> 1420 | I88: 44419 | J88: =VLOOKUP(I88,资产!$A:$AF,8,0)/100 -> 53034.95 | K88: =VLOOKUP(I88,资产!$A:$AF,9,0)/100 -> 3260.44 | L88: =VLOOKUP(I88,资产!$A:$AF,10,0)/100 -> 45686.39 | M88: =(VLOOKUP(I88,资产!$A:$AF,13,0)+VLOOKUP(I88,资产!$A:$AF,14,0)+VLOOKUP(I88,资产!$A:$AF,15,0))/100 -> 10440.81 | N88: =VLOOKUP(I88,资产!$A:$AF,16,0)/100 -> 20523.28 | O88: =VLOOKUP(I88,资产!$A:$AF,17,0)/100 -> 9679.87 | P88: =VLOOKUP(I88,资产!$A:$AF,18,0)/100 -> 12390.97 | Q88: =VLOOKUP(I88,资产!$A:$AF,20,0)/100 -> 23847.85 | R88: =VLOOKUP(I88,负债!$A:$P,5,0)/100 -> 41272.9 | S88: =VLOOKUP(I88,负债!$A:$P,6,0)/100 -> 3897.47 | T88: =VLOOKUP(I88,资产!$A:$AF,2,0)/100 -> 82571.59 | U88: =VLOOKUP(I88,资产!$A:$AF,7,0)/100 -> 76906.27 | V88: =VLOOKUP(I88,负债!$A:$P,9,0)/100 -> 12679.98 | W88: =VLOOKUP(I88,负债!$A:$P,6,0)/100 -> 3897.47 | X88: =VLOOKUP(I88,负债!$A:$P,2,0)/100 -> 82174.25 | Y88: =T88-V88-W88 -> 65994.14
A89: 1 | C89: * 市政流动性基金有限责任公司持有的净投资组合 | D89: =VLOOKUP($C$1,资产!$A:$AF,26,0) -> 0 | I89: 44426 | J89: =VLOOKUP(I89,资产!$A:$AF,8,0)/100 -> 53236.51 | K89: =VLOOKUP(I89,资产!$A:$AF,9,0)/100 -> 3260.44 | L89: =VLOOKUP(I89,资产!$A:$AF,10,0)/100 -> 45844.42 | M89: =(VLOOKUP(I89,资产!$A:$AF,13,0)+VLOOKUP(I89,资产!$A:$AF,14,0)+VLOOKUP(I89,资产!$A:$AF,15,0))/100 -> 10741.03 | N89: =VLOOKUP(I89,资产!$A:$AF,16,0)/100 -> 20212.45 | O89: =VLOOKUP(I89,资产!$A:$AF,17,0)/100 -> 9731.08 | P89: =VLOOKUP(I89,资产!$A:$AF,18,0)/100 -> 12551.94 | Q89: =VLOOKUP(I89,资产!$A:$AF,20,0)/100 -> 24656.38 | R89: =VLOOKUP(I89,负债!$A:$P,5,0)/100 -> 41621.65 | S89: =VLOOKUP(I89,负债!$A:$P,6,0)/100 -> 3136.51 | T89: =VLOOKUP(I89,资产!$A:$AF,2,0)/100 -> 83425.98 | U89: =VLOOKUP(I89,资产!$A:$AF,7,0)/100 -> 77916.36 | V89: =VLOOKUP(I89,负债!$A:$P,9,0)/100 -> 13854.01 | W89: =VLOOKUP(I89,负债!$A:$P,6,0)/100 -> 3136.51 | X89: =VLOOKUP(I89,负债!$A:$P,2,0)/100 -> 83028.56 | Y89: =T89-V89-W89 -> 66435.46
A90: 1 | C90: * 持有TALF II LLC投资组合净额 | D90: =VLOOKUP($C$1,资产!$A:$AF,27,0) -> 0 | I90: 44433 | J90: =VLOOKUP(I90,资产!$A:$AF,8,0)/100 -> 53463.72 | K90: =VLOOKUP(I90,资产!$A:$AF,9,0)/100 -> 3260.44 | L90: =VLOOKUP(I90,资产!$A:$AF,10,0)/100 -> 46040.44 | M90: =(VLOOKUP(I90,资产!$A:$AF,13,0)+VLOOKUP(I90,资产!$A:$AF,14,0)+VLOOKUP(I90,资产!$A:$AF,15,0))/100 -> 10741.71 | N90: =VLOOKUP(I90,资产!$A:$AF,16,0)/100 -> 20332.96 | O90: =VLOOKUP(I90,资产!$A:$AF,17,0)/100 -> 9814.87 | P90: =VLOOKUP(I90,资产!$A:$AF,18,0)/100 -> 12574.17 | Q90: =VLOOKUP(I90,资产!$A:$AF,20,0)/100 -> 24380.67 | R90: =VLOOKUP(I90,负债!$A:$P,5,0)/100 -> 42034.78 | S90: =VLOOKUP(I90,负债!$A:$P,6,0)/100 -> 2582 | T90: =VLOOKUP(I90,资产!$A:$AF,2,0)/100 -> 83327.43 | U90: =VLOOKUP(I90,资产!$A:$AF,7,0)/100 -> 77867.85 | V90: =VLOOKUP(I90,负债!$A:$P,9,0)/100 -> 14051.1 | W90: =VLOOKUP(I90,负债!$A:$P,6,0)/100 -> 2582 | X90: =VLOOKUP(I90,负债!$A:$P,2,0)/100 -> 82929.78 | Y90: =T90-V90-W90 -> 66694.33
A91: 1 | C91: * 托收中项目 | D91: =VLOOKUP($C$1,资产!$A:$AF,28,0) -> 53 | I91: 44440 | J91: =VLOOKUP(I91,资产!$A:$AF,8,0)/100 -> 53656.7 | K91: =VLOOKUP(I91,资产!$A:$AF,9,0)/100 -> 3260.44 | L91: =VLOOKUP(I91,资产!$A:$AF,10,0)/100 -> 46202.43 | M91: =(VLOOKUP(I91,资产!$A:$AF,13,0)+VLOOKUP(I91,资产!$A:$AF,14,0)+VLOOKUP(I91,资产!$A:$AF,15,0))/100 -> 10713.5 | N91: =VLOOKUP(I91,资产!$A:$AF,16,0)/100 -> 20492.68 | O91: =VLOOKUP(I91,资产!$A:$AF,17,0)/100 -> 9781.39 | P91: =VLOOKUP(I91,资产!$A:$AF,18,0)/100 -> 12669.13 | Q91: =VLOOKUP(I91,资产!$A:$AF,20,0)/100 -> 24380.68 | R91: =VLOOKUP(I91,负债!$A:$P,5,0)/100 -> 42064.49 | S91: =VLOOKUP(I91,负债!$A:$P,6,0)/100 -> 2969.34 | T91: =VLOOKUP(I91,资产!$A:$AF,2,0)/100 -> 83491.73 | U91: =VLOOKUP(I91,资产!$A:$AF,7,0)/100 -> 78060.85 | V91: =VLOOKUP(I91,负债!$A:$P,9,0)/100 -> 13762.96 | W91: =VLOOKUP(I91,负债!$A:$P,6,0)/100 -> 2969.34 | X91: =VLOOKUP(I91,负债!$A:$P,2,0)/100 -> 83093.78 | Y91: =T91-V91-W91 -> 66759.43
A92: 1 | C92: * 银行不动产 | D92: =VLOOKUP($C$1,资产!$A:$AF,29,0) -> 669 | I92: 44447 | J92: =VLOOKUP(I92,资产!$A:$AF,8,0)/100 -> 53727.41 | K92: =VLOOKUP(I92,资产!$A:$AF,9,0)/100 -> 3260.44 | L92: =VLOOKUP(I92,资产!$A:$AF,10,0)/100 -> 46268.44 | M92: =(VLOOKUP(I92,资产!$A:$AF,13,0)+VLOOKUP(I92,资产!$A:$AF,14,0)+VLOOKUP(I92,资产!$A:$AF,15,0))/100 -> 10713.86 | N92: =VLOOKUP(I92,资产!$A:$AF,16,0)/100 -> 20494.2 | O92: =VLOOKUP(I92,资产!$A:$AF,17,0)/100 -> 9814.98 | P92: =VLOOKUP(I92,资产!$A:$AF,18,0)/100 -> 12704.37 | Q92: =VLOOKUP(I92,资产!$A:$AF,20,0)/100 -> 24380.68 | R92: =VLOOKUP(I92,负债!$A:$P,5,0)/100 -> 42596.03 | S92: =VLOOKUP(I92,负债!$A:$P,6,0)/100 -> 2007.02 | T92: =VLOOKUP(I92,资产!$A:$AF,2,0)/100 -> 83573.14 | U92: =VLOOKUP(I92,资产!$A:$AF,7,0)/100 -> 78131.56 | V92: =VLOOKUP(I92,负债!$A:$P,9,0)/100 -> 14105.38 | W92: =VLOOKUP(I92,负债!$A:$P,6,0)/100 -> 2007.02 | X92: =VLOOKUP(I92,负债!$A:$P,2,0)/100 -> 83174.28 | Y92: =T92-V92-W92 -> 67460.74
A93: 1 | C93: * 中央银行流动性互换 | D93: =VLOOKUP($C$1,资产!$A:$AF,30,0) -> 16 | I93: 44454 | J93: =VLOOKUP(I93,资产!$A:$AF,8,0)/100 -> 53918.72 | K93: =VLOOKUP(I93,资产!$A:$AF,9,0)/100 -> 3260.44 | L93: =VLOOKUP(I93,资产!$A:$AF,10,0)/100 -> 46432.47 | M93: =(VLOOKUP(I93,资产!$A:$AF,13,0)+VLOOKUP(I93,资产!$A:$AF,14,0)+VLOOKUP(I93,资产!$A:$AF,15,0))/100 -> 10683.03 | N93: =VLOOKUP(I93,资产!$A:$AF,16,0)/100 -> 20579.6 | O93: =VLOOKUP(I93,资产!$A:$AF,17,0)/100 -> 9904.94 | P93: =VLOOKUP(I93,资产!$A:$AF,18,0)/100 -> 12751.16 | Q93: =VLOOKUP(I93,资产!$A:$AF,20,0)/100 -> 25141.56 | R93: =VLOOKUP(I93,负债!$A:$P,5,0)/100 -> 42446.77 | S93: =VLOOKUP(I93,负债!$A:$P,6,0)/100 -> 3446.68 | T93: =VLOOKUP(I93,资产!$A:$AF,2,0)/100 -> 84487.7 | U93: =VLOOKUP(I93,资产!$A:$AF,7,0)/100 -> 79083.75 | V93: =VLOOKUP(I93,负债!$A:$P,9,0)/100 -> 13756.76 | W93: =VLOOKUP(I93,负债!$A:$P,6,0)/100 -> 3446.68 | X93: =VLOOKUP(I93,负债!$A:$P,2,0)/100 -> 84089.07 | Y93: =T93-V93-W93 -> 67284.26
A94: 1 | C94: * 外币 | D94: =VLOOKUP($C$1,资产!$A:$AF,31,0) -> 19243 | I94: 44461 | J94: =VLOOKUP(I94,资产!$A:$AF,8,0)/100 -> 54133.74 | K94: =VLOOKUP(I94,资产!$A:$AF,9,0)/100 -> 3260.44 | L94: =VLOOKUP(I94,资产!$A:$AF,10,0)/100 -> 46608.48 | M94: =(VLOOKUP(I94,资产!$A:$AF,13,0)+VLOOKUP(I94,资产!$A:$AF,14,0)+VLOOKUP(I94,资产!$A:$AF,15,0))/100 -> 10755.52 | N94: =VLOOKUP(I94,资产!$A:$AF,16,0)/100 -> 20653.32 | O94: =VLOOKUP(I94,资产!$A:$AF,17,0)/100 -> 9949.88 | P94: =VLOOKUP(I94,资产!$A:$AF,18,0)/100 -> 12775.02 | Q94: =VLOOKUP(I94,资产!$A:$AF,20,0)/100 -> 25365.57 | R94: =VLOOKUP(I94,负债!$A:$P,5,0)/100 -> 41379.19 | S94: =VLOOKUP(I94,负债!$A:$P,6,0)/100 -> 2726.79 | T94: =VLOOKUP(I94,资产!$A:$AF,2,0)/100 -> 84898.24 | U94: =VLOOKUP(I94,资产!$A:$AF,7,0)/100 -> 79522.78 | V94: =VLOOKUP(I94,负债!$A:$P,9,0)/100 -> 15640.32 | W94: =VLOOKUP(I94,负债!$A:$P,6,0)/100 -> 2726.79 | X94: =VLOOKUP(I94,负债!$A:$P,2,0)/100 -> 84499.56 | Y94: =T94-V94-W94 -> 66531.13
A95: 1 | C95: * 其他联储资产 | D95: =VLOOKUP($C$1,资产!$A:$AF,32,0) -> 30333 | I95: 44468 | J95: =VLOOKUP(I95,资产!$A:$AF,8,0)/100 -> 54310.56 | K95: =VLOOKUP(I95,资产!$A:$AF,9,0)/100 -> 3260.44 | L95: =VLOOKUP(I95,资产!$A:$AF,10,0)/100 -> 46780.52 | M95: =(VLOOKUP(I95,资产!$A:$AF,13,0)+VLOOKUP(I95,资产!$A:$AF,14,0)+VLOOKUP(I95,资产!$A:$AF,15,0))/100 -> 10755.88 | N95: =VLOOKUP(I95,资产!$A:$AF,16,0)/100 -> 20932.84 | O95: =VLOOKUP(I95,资产!$A:$AF,17,0)/100 -> 9817.56 | P95: =VLOOKUP(I95,资产!$A:$AF,18,0)/100 -> 12804.27 | Q95: =VLOOKUP(I95,资产!$A:$AF,20,0)/100 -> 24946.84 | R95: =VLOOKUP(I95,负债!$A:$P,5,0)/100 -> 40948.1 | S95: =VLOOKUP(I95,负债!$A:$P,6,0)/100 -> 1737.45 | T95: =VLOOKUP(I95,资产!$A:$AF,2,0)/100 -> 84479.81 | U95: =VLOOKUP(I95,资产!$A:$AF,7,0)/100 -> 79280.87 | V95: =VLOOKUP(I95,负债!$A:$P,9,0)/100 -> 17023.47 | W95: =VLOOKUP(I95,负债!$A:$P,6,0)/100 -> 1737.45 | X95: =VLOOKUP(I95,负债!$A:$P,2,0)/100 -> 84081.07 | Y95: =T95-V95-W95 -> 65718.89
I96: 44475 | J96: =VLOOKUP(I96,资产!$A:$AF,8,0)/100 -> 54492.77 | K96: =VLOOKUP(I96,资产!$A:$AF,9,0)/100 -> 3260.44 | L96: =VLOOKUP(I96,资产!$A:$AF,10,0)/100 -> 46919.68 | M96: =(VLOOKUP(I96,资产!$A:$AF,13,0)+VLOOKUP(I96,资产!$A:$AF,14,0)+VLOOKUP(I96,资产!$A:$AF,15,0))/100 -> 10823.36 | N96: =VLOOKUP(I96,资产!$A:$AF,16,0)/100 -> 20853.01 | O96: =VLOOKUP(I96,资产!$A:$AF,17,0)/100 -> 9942.63 | P96: =VLOOKUP(I96,资产!$A:$AF,18,0)/100 -> 12873.78 | Q96: =VLOOKUP(I96,资产!$A:$AF,20,0)/100 -> 24947.49 | R96: =VLOOKUP(I96,负债!$A:$P,5,0)/100 -> 41675.44 | S96: =VLOOKUP(I96,负债!$A:$P,6,0)/100 -> 958.54 | T96: =VLOOKUP(I96,资产!$A:$AF,2,0)/100 -> 84640.32 | U96: =VLOOKUP(I96,资产!$A:$AF,7,0)/100 -> 79463.73 | V96: =VLOOKUP(I96,负债!$A:$P,9,0)/100 -> 17377.9 | W96: =VLOOKUP(I96,负债!$A:$P,6,0)/100 -> 958.54 | X96: =VLOOKUP(I96,负债!$A:$P,2,0)/100 -> 84241.8 | Y96: =T96-V96-W96 -> 66303.88
I97: 44482 | J97: =VLOOKUP(I97,资产!$A:$AF,8,0)/100 -> 54659.24 | K97: =VLOOKUP(I97,资产!$A:$AF,9,0)/100 -> 3260.44 | L97: =VLOOKUP(I97,资产!$A:$AF,10,0)/100 -> 47071.71 | M97: =(VLOOKUP(I97,资产!$A:$AF,13,0)+VLOOKUP(I97,资产!$A:$AF,14,0)+VLOOKUP(I97,资产!$A:$AF,15,0))/100 -> 10833.17 | N97: =VLOOKUP(I97,资产!$A:$AF,16,0)/100 -> 20968.02 | O97: =VLOOKUP(I97,资产!$A:$AF,17,0)/100 -> 9951.54 | P97: =VLOOKUP(I97,资产!$A:$AF,18,0)/100 -> 12906.52 | Q97: =VLOOKUP(I97,资产!$A:$AF,20,0)/100 -> 24947.59 | R97: =VLOOKUP(I97,负债!$A:$P,5,0)/100 -> 42045.1 | S97: =VLOOKUP(I97,负债!$A:$P,6,0)/100 -> 724.6 | T97: =VLOOKUP(I97,资产!$A:$AF,2,0)/100 -> 84809.42 | U97: =VLOOKUP(I97,资产!$A:$AF,7,0)/100 -> 79630.3 | V97: =VLOOKUP(I97,负债!$A:$P,9,0)/100 -> 16576.22 | W97: =VLOOKUP(I97,负债!$A:$P,6,0)/100 -> 724.6 | X97: =VLOOKUP(I97,负债!$A:$P,2,0)/100 -> 84410.79 | Y97: =T97-V97-W97 -> 67508.6
I98: 44489 | J98: =VLOOKUP(I98,资产!$A:$AF,8,0)/100 -> 54992.67 | K98: =VLOOKUP(I98,资产!$A:$AF,9,0)/100 -> 3260.44 | L98: =VLOOKUP(I98,资产!$A:$AF,10,0)/100 -> 47379.72 | M98: =(VLOOKUP(I98,资产!$A:$AF,13,0)+VLOOKUP(I98,资产!$A:$AF,14,0)+VLOOKUP(I98,资产!$A:$AF,15,0))/100 -> 10924.58 | N98: =VLOOKUP(I98,资产!$A:$AF,16,0)/100 -> 21088 | O98: =VLOOKUP(I98,资产!$A:$AF,17,0)/100 -> 10015.02 | P98: =VLOOKUP(I98,资产!$A:$AF,18,0)/100 -> 12965.09 | Q98: =VLOOKUP(I98,资产!$A:$AF,20,0)/100 -> 25469.32 | R98: =VLOOKUP(I98,负债!$A:$P,5,0)/100 -> 40503.43 | S98: =VLOOKUP(I98,负债!$A:$P,6,0)/100 -> 1173.64 | T98: =VLOOKUP(I98,资产!$A:$AF,2,0)/100 -> 85649.43 | U98: =VLOOKUP(I98,资产!$A:$AF,7,0)/100 -> 80485.46 | V98: =VLOOKUP(I98,负债!$A:$P,9,0)/100 -> 17863.68 | W98: =VLOOKUP(I98,负债!$A:$P,6,0)/100 -> 1173.64 | X98: =VLOOKUP(I98,负债!$A:$P,2,0)/100 -> 85250.83 | Y98: =T98-V98-W98 -> 66612.11
I99: 44496 | J99: =VLOOKUP(I99,资产!$A:$AF,8,0)/100 -> 55133.29 | K99: =VLOOKUP(I99,资产!$A:$AF,9,0)/100 -> 3260.44 | L99: =VLOOKUP(I99,资产!$A:$AF,10,0)/100 -> 47505.74 | M99: =(VLOOKUP(I99,资产!$A:$AF,13,0)+VLOOKUP(I99,资产!$A:$AF,14,0)+VLOOKUP(I99,资产!$A:$AF,15,0))/100 -> 10924.72 | N99: =VLOOKUP(I99,资产!$A:$AF,16,0)/100 -> 21138.12 | O99: =VLOOKUP(I99,资产!$A:$AF,17,0)/100 -> 10066.65 | P99: =VLOOKUP(I99,资产!$A:$AF,18,0)/100 -> 13003.8 | Q99: =VLOOKUP(I99,资产!$A:$AF,20,0)/100 -> 25277.77 | R99: =VLOOKUP(I99,负债!$A:$P,5,0)/100 -> 41231.54 | S99: =VLOOKUP(I99,负债!$A:$P,6,0)/100 -> 2364.95 | T99: =VLOOKUP(I99,资产!$A:$AF,2,0)/100 -> 85561.81 | U99: =VLOOKUP(I99,资产!$A:$AF,7,0)/100 -> 80434.53 | V99: =VLOOKUP(I99,负债!$A:$P,9,0)/100 -> 17214.84 | W99: =VLOOKUP(I99,负债!$A:$P,6,0)/100 -> 2364.95 | X99: =VLOOKUP(I99,负债!$A:$P,2,0)/100 -> 85163.18 | Y99: =T99-V99-W99 -> 65982.02
I100: 44503 | J100: =VLOOKUP(I100,资产!$A:$AF,8,0)/100 -> 55332.19 | K100: =VLOOKUP(I100,资产!$A:$AF,9,0)/100 -> 3260.44 | L100: =VLOOKUP(I100,资产!$A:$AF,10,0)/100 -> 47677.76 | M100: =(VLOOKUP(I100,资产!$A:$AF,13,0)+VLOOKUP(I100,资产!$A:$AF,14,0)+VLOOKUP(I100,资产!$A:$AF,15,0))/100 -> 11030.98 | N100: =VLOOKUP(I100,资产!$A:$AF,16,0)/100 -> 21210.68 | O100: =VLOOKUP(I100,资产!$A:$AF,17,0)/100 -> 10013.73 | P100: =VLOOKUP(I100,资产!$A:$AF,18,0)/100 -> 13076.8 | Q100: =VLOOKUP(I100,资产!$A:$AF,20,0)/100 -> 25278.24 | R100: =VLOOKUP(I100,负债!$A:$P,5,0)/100 -> 41498.3 | S100: =VLOOKUP(I100,负债!$A:$P,6,0)/100 -> 2869.59 | T100: =VLOOKUP(I100,资产!$A:$AF,2,0)/100 -> 85748.71 | U100: =VLOOKUP(I100,资产!$A:$AF,7,0)/100 -> 80633.9 | V100: =VLOOKUP(I100,负债!$A:$P,9,0)/100 -> 16570.66 | W100: =VLOOKUP(I100,负债!$A:$P,6,0)/100 -> 2869.59 | X100: =VLOOKUP(I100,负债!$A:$P,2,0)/100 -> 85350.05 | Y100: =T100-V100-W100 -> 66308.46
I101: 44510 | J101: =VLOOKUP(I101,资产!$A:$AF,8,0)/100 -> 55526.07 | K101: =VLOOKUP(I101,资产!$A:$AF,9,0)/100 -> 3260.44 | L101: =VLOOKUP(I101,资产!$A:$AF,10,0)/100 -> 47855.76 | M101: =(VLOOKUP(I101,资产!$A:$AF,13,0)+VLOOKUP(I101,资产!$A:$AF,14,0)+VLOOKUP(I101,资产!$A:$AF,15,0))/100 -> 11031.23 | N101: =VLOOKUP(I101,资产!$A:$AF,16,0)/100 -> 21319.56 | O101: =VLOOKUP(I101,资产!$A:$AF,17,0)/100 -> 10055.51 | P101: =VLOOKUP(I101,资产!$A:$AF,18,0)/100 -> 13119.78 | Q101: =VLOOKUP(I101,资产!$A:$AF,20,0)/100 -> 25933.66 | R101: =VLOOKUP(I101,负债!$A:$P,5,0)/100 -> 41785.86 | S101: =VLOOKUP(I101,负债!$A:$P,6,0)/100 -> 2314.21 | T101: =VLOOKUP(I101,资产!$A:$AF,2,0)/100 -> 86631.17 | U101: =VLOOKUP(I101,资产!$A:$AF,7,0)/100 -> 81483.2 | V101: =VLOOKUP(I101,负债!$A:$P,9,0)/100 -> 17529.77 | W101: =VLOOKUP(I101,负债!$A:$P,6,0)/100 -> 2314.21 | X101: =VLOOKUP(I101,负债!$A:$P,2,0)/100 -> 86232.08 | Y101: =T101-V101-W101 -> 66787.19
I102: 44517 | J102: =VLOOKUP(I102,资产!$A:$AF,8,0)/100 -> 55735.25 | K102: =VLOOKUP(I102,资产!$A:$AF,9,0)/100 -> 3260.44 | L102: =VLOOKUP(I102,资产!$A:$AF,10,0)/100 -> 48062.55 | M102: =(VLOOKUP(I102,资产!$A:$AF,13,0)+VLOOKUP(I102,资产!$A:$AF,14,0)+VLOOKUP(I102,资产!$A:$AF,15,0))/100 -> 11088.84 | N102: =VLOOKUP(I102,资产!$A:$AF,16,0)/100 -> 21278.92 | O102: =VLOOKUP(I102,资产!$A:$AF,17,0)/100 -> 10088.48 | P102: =VLOOKUP(I102,资产!$A:$AF,18,0)/100 -> 13279.01 | Q102: =VLOOKUP(I102,资产!$A:$AF,20,0)/100 -> 26034.31 | R102: =VLOOKUP(I102,负债!$A:$P,5,0)/100 -> 41888.37 | S102: =VLOOKUP(I102,负债!$A:$P,6,0)/100 -> 1789.72 | T102: =VLOOKUP(I102,资产!$A:$AF,2,0)/100 -> 86749.7 | U102: =VLOOKUP(I102,资产!$A:$AF,7,0)/100 -> 81793.03 | V102: =VLOOKUP(I102,负债!$A:$P,9,0)/100 -> 18142.92 | W102: =VLOOKUP(I102,负债!$A:$P,6,0)/100 -> 1789.72 | X102: =VLOOKUP(I102,负债!$A:$P,2,0)/100 -> 86343.3 | Y102: =T102-V102-W102 -> 66817.06
I103: 44524 | J103: =VLOOKUP(I103,资产!$A:$AF,8,0)/100 -> 55789 | K103: =VLOOKUP(I103,资产!$A:$AF,9,0)/100 -> 3260.44 | L103: =VLOOKUP(I103,资产!$A:$AF,10,0)/100 -> 48092.32 | M103: =(VLOOKUP(I103,资产!$A:$AF,13,0)+VLOOKUP(I103,资产!$A:$AF,14,0)+VLOOKUP(I103,资产!$A:$AF,15,0))/100 -> 11089.08 | N103: =VLOOKUP(I103,资产!$A:$AF,16,0)/100 -> 21298.29 | O103: =VLOOKUP(I103,资产!$A:$AF,17,0)/100 -> 10092.04 | P103: =VLOOKUP(I103,资产!$A:$AF,18,0)/100 -> 13309.59 | Q103: =VLOOKUP(I103,资产!$A:$AF,20,0)/100 -> 26097.26 | R103: =VLOOKUP(I103,负债!$A:$P,5,0)/100 -> 41728.07 | S103: =VLOOKUP(I103,负债!$A:$P,6,0)/100 -> 1410.42 | T103: =VLOOKUP(I103,资产!$A:$AF,2,0)/100 -> 86817.71 | U103: =VLOOKUP(I103,资产!$A:$AF,7,0)/100 -> 81909.73 | V103: =VLOOKUP(I103,负债!$A:$P,9,0)/100 -> 17588.15 | W103: =VLOOKUP(I103,负债!$A:$P,6,0)/100 -> 1410.42 | X103: =VLOOKUP(I103,负债!$A:$P,2,0)/100 -> 86411.25 | Y103: =T103-V103-W103 -> 67819.14
I104: 44531 | J104: =VLOOKUP(I104,资产!$A:$AF,8,0)/100 -> 55921.19 | K104: =VLOOKUP(I104,资产!$A:$AF,9,0)/100 -> 3260.44 | L104: =VLOOKUP(I104,资产!$A:$AF,10,0)/100 -> 48198.04 | M104: =(VLOOKUP(I104,资产!$A:$AF,13,0)+VLOOKUP(I104,资产!$A:$AF,14,0)+VLOOKUP(I104,资产!$A:$AF,15,0))/100 -> 11213.04 | N104: =VLOOKUP(I104,资产!$A:$AF,16,0)/100 -> 21298.18 | O104: =VLOOKUP(I104,资产!$A:$AF,17,0)/100 -> 10061.38 | P104: =VLOOKUP(I104,资产!$A:$AF,18,0)/100 -> 13348.59 | Q104: =VLOOKUP(I104,资产!$A:$AF,20,0)/100 -> 25708.84 | R104: =VLOOKUP(I104,负债!$A:$P,5,0)/100 -> 42660.22 | S104: =VLOOKUP(I104,负债!$A:$P,6,0)/100 -> 1591.48 | T104: =VLOOKUP(I104,资产!$A:$AF,2,0)/100 -> 86504.02 | U104: =VLOOKUP(I104,资产!$A:$AF,7,0)/100 -> 81653.51 | V104: =VLOOKUP(I104,负债!$A:$P,9,0)/100 -> 17292.77 | W104: =VLOOKUP(I104,负债!$A:$P,6,0)/100 -> 1591.48 | X104: =VLOOKUP(I104,负债!$A:$P,2,0)/100 -> 86097.49 | Y104: =T104-V104-W104 -> 67619.77
I105: 44538 | J105: =VLOOKUP(I105,资产!$A:$AF,8,0)/100 -> 56041.69 | K105: =VLOOKUP(I105,资产!$A:$AF,9,0)/100 -> 3260.44 | L105: =VLOOKUP(I105,资产!$A:$AF,10,0)/100 -> 48280.3 | M105: =(VLOOKUP(I105,资产!$A:$AF,13,0)+VLOOKUP(I105,资产!$A:$AF,14,0)+VLOOKUP(I105,资产!$A:$AF,15,0))/100 -> 11213.65 | N105: =VLOOKUP(I105,资产!$A:$AF,16,0)/100 -> 21345.49 | O105: =VLOOKUP(I105,资产!$A:$AF,17,0)/100 -> 10096.97 | P105: =VLOOKUP(I105,资产!$A:$AF,18,0)/100 -> 13385.58 | Q105: =VLOOKUP(I105,资产!$A:$AF,20,0)/100 -> 25709.18 | R105: =VLOOKUP(I105,负债!$A:$P,5,0)/100 -> 42556 | S105: =VLOOKUP(I105,负债!$A:$P,6,0)/100 -> 1251.44 | T105: =VLOOKUP(I105,资产!$A:$AF,2,0)/100 -> 86645.24 | U105: =VLOOKUP(I105,资产!$A:$AF,7,0)/100 -> 81774.35 | V105: =VLOOKUP(I105,负债!$A:$P,9,0)/100 -> 17872.27 | W105: =VLOOKUP(I105,负债!$A:$P,6,0)/100 -> 1251.44 | X105: =VLOOKUP(I105,负债!$A:$P,2,0)/100 -> 86238.68 | Y105: =T105-V105-W105 -> 67521.53
I106: 44545 | J106: =VLOOKUP(I106,资产!$A:$AF,8,0)/100 -> 56382.89 | K106: =VLOOKUP(I106,资产!$A:$AF,9,0)/100 -> 3260.44 | L106: =VLOOKUP(I106,资产!$A:$AF,10,0)/100 -> 48613.07 | M106: =(VLOOKUP(I106,资产!$A:$AF,13,0)+VLOOKUP(I106,资产!$A:$AF,14,0)+VLOOKUP(I106,资产!$A:$AF,15,0))/100 -> 11239.7 | N106: =VLOOKUP(I106,资产!$A:$AF,16,0)/100 -> 21512.4 | O106: =VLOOKUP(I106,资产!$A:$AF,17,0)/100 -> 10180.9 | P106: =VLOOKUP(I106,资产!$A:$AF,18,0)/100 -> 13449.88 | Q106: =VLOOKUP(I106,资产!$A:$AF,20,0)/100 -> 26281.3 | R106: =VLOOKUP(I106,负债!$A:$P,5,0)/100 -> 42736.34 | S106: =VLOOKUP(I106,负债!$A:$P,6,0)/100 -> 582.94 | T106: =VLOOKUP(I106,资产!$A:$AF,2,0)/100 -> 87566.66 | U106: =VLOOKUP(I106,资产!$A:$AF,7,0)/100 -> 82687.66 | V106: =VLOOKUP(I106,负债!$A:$P,9,0)/100 -> 19278.79 | W106: =VLOOKUP(I106,负债!$A:$P,6,0)/100 -> 582.94 | X106: =VLOOKUP(I106,负债!$A:$P,2,0)/100 -> 87160.01 | Y106: =T106-V106-W106 -> 67704.93
I107: 44552 | J107: =VLOOKUP(I107,资产!$A:$AF,8,0)/100 -> 56498.23 | K107: =VLOOKUP(I107,资产!$A:$AF,9,0)/100 -> 3260.44 | L107: =VLOOKUP(I107,资产!$A:$AF,10,0)/100 -> 48692.08 | M107: =(VLOOKUP(I107,资产!$A:$AF,13,0)+VLOOKUP(I107,资产!$A:$AF,14,0)+VLOOKUP(I107,资产!$A:$AF,15,0))/100 -> 11240.31 | N107: =VLOOKUP(I107,资产!$A:$AF,16,0)/100 -> 21537.42 | O107: =VLOOKUP(I107,资产!$A:$AF,17,0)/100 -> 10232.31 | P107: =VLOOKUP(I107,资产!$A:$AF,18,0)/100 -> 13488.18 | Q107: =VLOOKUP(I107,资产!$A:$AF,20,0)/100 -> 26496.61 | R107: =VLOOKUP(I107,负债!$A:$P,5,0)/100 -> 41049.26 | S107: =VLOOKUP(I107,负债!$A:$P,6,0)/100 -> 1975.16 | T107: =VLOOKUP(I107,资产!$A:$AF,2,0)/100 -> 87904.95 | U107: =VLOOKUP(I107,资产!$A:$AF,7,0)/100 -> 83018.31 | V107: =VLOOKUP(I107,负债!$A:$P,9,0)/100 -> 19829.15 | W107: =VLOOKUP(I107,负债!$A:$P,6,0)/100 -> 1975.16 | X107: =VLOOKUP(I107,负债!$A:$P,2,0)/100 -> 87498.34 | Y107: =T107-V107-W107 -> 66100.64
... I337: 46162 | J337: =VLOOKUP(I337,资产!$A:$AF,8,0)/100 -> 44577.12 | K337: =VLOOKUP(I337,资产!$A:$AF,9,0)/100 -> 4596.07 | L337: =VLOOKUP(I337,资产!$A:$AF,10,0)/100 -> 36153.93 | M337: =(VLOOKUP(I337,资产!$A:$AF,13,0)+VLOOKUP(I337,资产!$A:$AF,14,0)+VLOOKUP(I337,资产!$A:$AF,15,0))/100 -> 9376.82 | N337: =VLOOKUP(I337,资产!$A:$AF,16,0)/100 -> 14298.8 | O337: =VLOOKUP(I337,资产!$A:$AF,17,0)/100 -> 4812.58 | P337: =VLOOKUP(I337,资产!$A:$AF,18,0)/100 -> 16088.92 | Q337: =VLOOKUP(I337,资产!$A:$AF,20,0)/100 -> 19776.61 | R337: =VLOOKUP(I337,负债!$A:$P,5,0)/100 -> 31067.16 | S337: =VLOOKUP(I337,负债!$A:$P,6,0)/100 -> 7819.79 | T337: =VLOOKUP(I337,资产!$A:$AF,2,0)/100 -> 67136.43 | U337: =VLOOKUP(I337,资产!$A:$AF,7,0)/100 -> 64377.19 | V337: =VLOOKUP(I337,负债!$A:$P,9,0)/100 -> 3426.28 | W337: =VLOOKUP(I337,负债!$A:$P,6,0)/100 -> 7819.79 | X337: =VLOOKUP(I337,负债!$A:$P,2,0)/100 -> 66664.07 | Y337: =T337-V337-W337 -> 55890.36

Sheet 资产
A4: 开始日期 | B4: 37257
A5: 截止日期 | B5: 当前日期
A6: EDBclose | B6: EDBclose
A7: 日期 | B7: 美国:所有联储银行:资产:总资产 | C7: 美国:所有联储银行:资产:黄金证券账户 | D7: 美国:所有联储银行:资产:特别提款权账户 | E7: 美国:所有联储银行:资产:硬币 | F7: 美国:所有联储银行:资产:持有证券、未摊销证券溢价和折扣、回购协议和贷款 | G7: 美国:所有联储银行:资产:持有证券 | H7: 美国:所有联储银行:资产:持有证券:美国国债 | I7: 美国:所有联储银行:资产:持有证券:美国国债:短期债券 | J7: 美国:所有联储银行:资产:持有证券:美国国债:中长期名义债券 | K7: 美国:所有联储银行:资产:持有证券:美国国债:中长期通胀指数债券 | L7: 美国:所有联储银行:资产:持有证券:美国国债:通胀补偿 | M7: 美国:所有联储银行:资产:持有证券:美国国债:15天以内 | N7: 美国:所有联储银行:资产:持有证券:美国国债:16-90天 | O7: 美国:所有联储银行:资产:持有证券:美国国债:91天-1年 | P7: 美国:所有联储银行:资产:持有证券:美国国债:1-5年 | Q7: 美国:所有联储银行:资产:持有证券:美国国债:5-10年 | R7: 美国:所有联储银行:资产:持有证券:美国国债:大于10年 | S7: 美国:所有联储银行:资产:持有证券:联邦机构债券 | T7: 美国:所有联储银行:资产:持有证券:抵押贷款支持债券(MBS) | U7: 美国:所有联储银行:资产:当前持有的未摊销证券溢价 | V7: 美国:所有联储银行:资产:当前持有的未摊销证券折扣 | W7: 美国:所有联储银行:资产:正向回购协议 | X7: 美国:所有联储银行:资产:其他贷款 | Y7: 美国:所有联储银行:资产:储备银行信贷:MS Facilities LLC的净投资组合持有量(中产阶级贷款计划) | Z7: 美国:所有联储银行:资产:储备银行信贷:市政流动性基金有限责任公司持有的净投资组合 | AA7: 美国:所有联储银行:资产:持有TALF II LLC投资组合净额 | AB7: 美国:所有联储银行:资产:托收中项目 | AC7: 美国:所有联储银行:资产:银行不动产 | AD7: 美国:所有联储银行:资产:中央银行流动性互换 | AE7: 美国:所有联储银行:资产:外币 | AF7: 美国:所有联储银行:资产:其他联储资产
A8: Date | B8: G1100075 | C8: G1100051 | D8: G1100052 | E8: G1100053 | F8: G1100054 | G8: G1100055 | H8: G1100056 | I8: G1100057 | J8: G1100058 | K8: G1100059 | L8: G1100060 | M8: N8556218 | N8: J9380603 | O8: T0219969 | P8: Z3240916 | Q8: J1003369 | R8: P9897035 | S8: G1100061 | T8: G1100062 | U8: G1137382 | V8: G1137383 | W8: G1100063 | X8: G1100065 | Y8: G1169233 | Z8: G1169234 | AA8: G1169236 | AB8: G1100071 | AC8: G1100072 | AD8: G1100073 | AE8: G1137384 | AF8: G1100074
A9: 37608 | B9: =[1]!WSD(B8:AF8,B6,B4,B5,"TradingCalendar=SSE","PriceAdj=","rptType=1","Version=1","ShowParams=Y","cols=31;rows=1223") -> 719542 | C9: 11039 | D9: 2200 | E9: 1035 | F9: 669223 | G9: 629407 | H9: 629397 | I9: 226682 | J9: 389219 | K9: 12242 | L9: 1253 | M9: 47253 | N9: 134262 | O9: 140816 | P9: 173935 | Q9: 53295 | R9: 79836 | S9: 10 | T9: 0 | U9: 10829 | V9: -1058 | W9: 30000 | X9: 45 | AB9: 8800 | AC9: 1534 | AD9: 0 | AE9: 16551 | AF9: 9161
A10: 37615 | B10: 732059 | C10: 11039 | D10: 2200 | E10: 1011 | F10: 676466 | G10: 629412 | H10: 629402 | I10: 226682 | J10: 389219 | K10: 12242 | L10: 1258 | M10: 33670 | N10: 146846 | O10: 141815 | P10: 173936 | Q10: 53298 | R10: 79838 | S10: 10 | T10: 0 | U10: 10793 | V10: -1048 | W10: 37250 | X10: 59 | AB10: 13239 | AC10: 1540 | AD10: 0 | AE10: 16655 | AF10: 9909
A11: 37622 | B11: 730994 | C11: 11039 | D11: 2200 | E11: 988 | F11: 678665 | G11: 629416 | H11: 629406 | I11: 226682 | J11: 389219 | K11: 12242 | L11: 1263 | M11: 27444 | N11: 154225 | O11: 141840 | P11: 172758 | Q11: 53300 | R11: 79840 | S11: 10 | T11: 0 | U11: 10762 | V11: -1054 | W11: 39500 | X11: 40 | AB11: 10291 | AC11: 1543 | AD11: 0 | AE11: 16913 | AF11: 9356
A12: 37629 | B12: 723762 | C12: 11039 | D12: 2200 | E12: 996 | F12: 672872 | G12: 629416 | H12: 629406 | I12: 226682 | J12: 389219 | K12: 12242 | L12: 1263 | M12: 42439 | N12: 138513 | O12: 142557 | P12: 172758 | Q12: 53300 | R12: 79840 | S12: 10 | T12: 0 | U12: 10722 | V12: -1034 | W12: 33750 | X12: 18 | AB12: 8353 | AC12: 1541 | AD12: 0 | AE12: 16847 | AF12: 9914
A13: 37636 | B13: 720074 | C13: 11039 | D13: 2200 | E13: 1043 | F13: 669094 | G13: 629416 | H13: 629406 | I13: 226682 | J13: 389219 | K13: 12242 | L13: 1263 | M13: 43631 | N13: 136918 | O13: 142959 | P13: 174818 | Q13: 51240 | R13: 79840 | S13: 10 | T13: 0 | U13: 10687 | V13: -1024 | W13: 30000 | X13: 15 | AB13: 8155 | AC13: 1542 | AD13: 0 | AE13: 17060 | AF13: 9942
A14: 37643 | B14: 735953 | C14: 11039 | D14: 2200 | E14: 1085 | F14: 675815 | G14: 629416 | H14: 629406 | I14: 226682 | J14: 389219 | K14: 12242 | L14: 1263 | M14: 50618 | N14: 129676 | O14: 143215 | P14: 174818 | Q14: 51240 | R14: 79840 | S14: 10 | T14: 0 | U14: 10652 | V14: -1016 | W14: 36750 | X14: 13 | AB14: 16652 | AC14: 1541 | AD14: 0 | AE14: 17180 | AF14: 10442
A15: 37650 | B15: 712809 | C15: 11039 | D15: 2200 | E15: 1111 | F15: 659535 | G15: 629416 | H15: 629406 | I15: 226682 | J15: 389219 | K15: 12242 | L15: 1263 | M15: 49592 | N15: 130709 | O15: 143207 | P15: 174818 | Q15: 51240 | R15: 79840 | S15: 10 | T15: 0 | U15: 10617 | V15: -1009 | W15: 20500 | X15: 11 | AB15: 9250 | AC15: 1543 | AD15: 0 | AE15: 17299 | AF15: 10831
A16: 37657 | B16: 719643 | C16: 11039 | D16: 2200 | E16: 1134 | F16: 666743 | G16: 629411 | H16: 629401 | I16: 226682 | J16: 389219 | K16: 12242 | L16: 1257 | M16: 45981 | N16: 134667 | O16: 142243 | P16: 175434 | Q16: 51239 | R16: 79837 | S16: 10 | T16: 0 | U16: 10582 | V16: -1016 | W16: 27750 | X16: 15 | AB16: 8959 | AC16: 1539 | AD16: 0 | AE16: 17178 | AF16: 10850
A17: 37664 | B17: 713281 | C17: 11039 | D17: 2200 | E17: 1142 | F17: 661276 | G17: 630957 | H17: 630947 | I17: 227238 | J17: 390217 | K17: 12242 | L17: 1250 | M17: 44507 | N17: 136637 | O17: 142780 | P17: 175832 | Q17: 51356 | R17: 79834 | S17: 10 | T17: 0 | U17: 10580 | V17: -1011 | W17: 20746 | X17: 4 | AB17: 7829 | AC17: 1541 | AD17: 0 | AE17: 16977 | AF17: 11276
A18: 37671 | B18: 730400 | C18: 11039 | D18: 2200 | E18: 1123 | F18: 675312 | G18: 631273 | H18: 631263 | I18: 227561 | J18: 390217 | K18: 12242 | L18: 1242 | M18: 46317 | N18: 131154 | O18: 145010 | P18: 177990 | Q18: 50961 | R18: 79831 | S18: 10 | T18: 0 | U18: 10546 | V18: -1021 | W18: 34496 | X18: 17 | AB18: 14167 | AC18: 1557 | AD18: 0 | AE18: 17180 | AF18: 7821
A19: 37678 | B19: 721980 | C19: 11039 | D19: 2200 | E19: 1100 | F19: 671334 | G19: 636006 | H19: 635996 | I19: 230606 | J19: 391913 | K19: 12242 | L19: 1235 | M19: 45075 | N19: 133699 | O19: 146752 | P19: 178982 | Q19: 51659 | R19: 79828 | S19: 10 | T19: 0 | U19: 10577 | V19: -1004 | W19: 25750 | X19: 6 | AB19: 9197 | AC19: 1557 | AD19: 0 | AE19: 17330 | AF19: 8223
A20: 37685 | B20: 722649 | C20: 11039 | D20: 2200 | E20: 1080 | F20: 670028 | G20: 637149 | H20: 637139 | I20: 231061 | J20: 392593 | K20: 12242 | L20: 1242 | M20: 35519 | N20: 140723 | O20: 149160 | P20: 180176 | Q20: 51730 | R20: 79831 | S20: 10 | T20: 0 | U20: 10617 | V20: -998 | W20: 23250 | X20: 11 | AB20: 10984 | AC20: 1555 | AD20: 0 | AE20: 17473 | AF20: 8291
A21: 37692 | B21: 717014 | C21: 11039 | D21: 2200 | E21: 1070 | F21: 667105 | G21: 638724 | H21: 638714 | I21: 231305 | J21: 393911 | K21: 12242 | L21: 1256 | M21: 35307 | N21: 141821 | O21: 149837 | P21: 180179 | Q21: 51734 | R21: 79837 | S21: 10 | T21: 0 | U21: 10609 | V21: -987 | W21: 18750 | X21: 9 | AB21: 7890 | AC21: 1557 | AD21: 0 | AE21: 17536 | AF21: 8618
... A919: 43978 | B919: 7097316 | C919: 11037 | D919: 5200 | E919: 1447 | F919: 6533722 | G919: 5946969 | H919: 4109512 | I919: 326044 | J919: 3489174 | K919: 257451 | L919: 36843 | M919: 55608 | N919: 279039 | O919: 564220 | P919: 1577552 | Q919: 719915 | R919: 913177 | S919: 2347 | T919: 1835110 | U919: 304256 | V919: -5500 | W919: 181101 | X919: 106896 | AB919: 67 | AC919: 2205 | AD919: 448946 | AE919: 20564 | AF919: 26482
A920: 43985 | B920: 7165217 | C920: 11037 | D920: 5200 | E920: 1434 | F920: 6585568 | G920: 5972297 | H920: 4134356 | I920: 326044 | J920: 3512424 | K920: 259151 | L920: 36737 | M920: 49583 | N920: 283619 | O920: 589247 | P920: 1575173 | Q920: 719393 | R920: 917341 | S920: 2347 | T920: 1835594 | U920: 305269 | V920: -5504 | W920: 211550 | X920: 101956 | Z920: 16075 | AB920: 41 | AC920: 2198 | AD920: 446945 | AE920: 20768 | AF920: 27002
A921: 43992 | B921: 7168936 | C921: 11037 | D921: 5200 | E921: 1412 | F921: 6555242 | G921: 5988351 | H921: 4150409 | I921: 326044 | J921: 3526774 | K921: 261151 | L921: 36440 | M921: 42873 | N921: 292827 | O921: 586718 | P921: 1581035 | Q921: 725316 | R921: 921640 | S921: 2347 | T921: 1835595 | U921: 306816 | V921: -5452 | W921: 167300 | X921: 98227 | Y921: 31875 | Z921: 16077 | AB921: 40 | AC921: 2201 | AD921: 444520 | AE921: 21015 | AF921: 30147
A922: 43999 | B922: 7094690 | C922: 11037 | D922: 5200 | E922: 1431 | F922: 6570172 | G922: 6090428 | H922: 4169340 | I922: 326044 | J922: 3542389 | K922: 264552 | L922: 36356 | M922: 70365 | N922: 276151 | O922: 587886 | P922: 1581775 | Q922: 729159 | R922: 924006 | S922: 2347 | T922: 1918741 | U922: 311026 | V922: -5366 | W922: 79053 | X922: 95031 | Y922: 31876 | Z922: 16079 | AB922: 51 | AC922: 2202 | AD922: 352470 | AE922: 20866 | AF922: 31594
A923: 44006 | B923: 7082302 | C923: 11037 | D923: 5200 | E923: 1455 | F923: 6617290 | G923: 6143193 | H923: 4197404 | I923: 326044 | J923: 3570924 | K923: 264552 | L923: 35884 | M923: 64328 | N923: 274008 | O923: 605122 | P923: 1592447 | Q923: 735883 | R923: 925617 | S923: 2347 | T923: 1943441 | U923: 313854 | V923: -5319 | W923: 70201 | X923: 95360 | Y923: 37502 | Z923: 16080 | AA923: 8500 | AB923: 73 | AC923: 2202 | AD923: 274963 | AE923: 20958 | AF923: 33628
A924: 44013 | B924: 7009040 | C924: 11037 | D924: 5200 | E924: 1475 | F924: 6594261 | G924: 6126948 | H924: 4213220 | I924: 326044 | J924: 3581139 | K924: 270206 | L924: 35831 | M924: 64471 | N924: 250820 | O924: 635460 | P924: 1597928 | Q924: 732150 | R924: 932391 | S924: 2347 | T924: 1911381 | U924: 314324 | V924: -5345 | W924: 61201 | X924: 97133 | Y924: 37502 | Z924: 16081 | AA924: 8753 | AB924: 46 | AC924: 2193 | AD924: 225414 | AE924: 20984 | AF924: 31355
A925: 44020 | B925: 6920716 | C925: 11037 | D925: 5200 | E925: 1497 | F925: 6548409 | G925: 6145103 | H925: 4231355 | I925: 326044 | J925: 3599273 | K925: 270206 | L925: 35833 | M925: 66114 | N925: 270043 | O925: 618085 | P925: 1607239 | Q925: 735426 | R925: 934448 | S925: 2347 | T925: 1911401 | U925: 315251 | V925: -5299 | W925: 0 | X925: 93355 | Y925: 37503 | Z925: 16082 | AA925: 8753 | AB925: 51 | AC925: 2196 | AD925: 179095 | AE925: 20973 | AF925: 34473
A926: 44027 | B926: 6958604 | C926: 11037 | D926: 5200 | E926: 1523 | F926: 6610048 | G926: 6203965 | H926: 4253229 | I926: 326044 | J926: 3625089 | K926: 266914 | L926: 35182 | M926: 58895 | N926: 279380 | O926: 633384 | P926: 1604839 | Q926: 738129 | R926: 938604 | S926: 2347 | T926: 1948388 | U926: 317957 | V926: -5280 | W926: 2 | X926: 93404 | Y926: 37515 | Z926: 16084 | AA926: 9439 | AB926: 53 | AC926: 2198 | AD926: 154850 | AE926: 21094 | AF926: 35481
A927: 44034 | B927: 6964755 | C927: 11037 | D927: 5200 | E927: 1522 | F927: 6646714 | G927: 6238825 | H927: 4265878 | I927: 326044 | J927: 3636425 | K927: 268113 | L927: 35296 | M927: 74899 | N927: 259225 | O927: 637534 | P927: 1607135 | Q927: 745867 | R927: 941219 | S927: 2347 | T927: 1970600 | U927: 320498 | V927: -5161 | W927: 0 | X927: 92552 | Y927: 37518 | Z927: 16085 | AA927: 9439 | AB927: 52 | AC927: 2199 | AD927: 121992 | AE927: 21267 | AF927: 37579
A928: 44041 | B928: 6949032 | C928: 11037 | D928: 5200 | E928: 1522 | F928: 6635516 | G928: 6229291 | H928: 4293563 | I928: 326044 | J928: 3661492 | K928: 270514 | L928: 35513 | M928: 75015 | N928: 256470 | O928: 644020 | P928: 1627218 | Q928: 746156 | R928: 944684 | S928: 2347 | T928: 1933380 | U928: 320706 | V928: -5004 | W928: 0 | X928: 90523 | Y928: 37588 | Z928: 16086 | AA928: 9439 | AB928: 57 | AC928: 2200 | AD928: 117473 | AE928: 21641 | AF928: 38163
A929: 44048 | B929: 6945237 | C929: 11037 | D929: 5200 | E929: 1533 | F929: 6642261 | G929: 6241464 | H929: 4305651 | I929: 326044 | J929: 3670435 | K929: 273306 | L929: 35866 | M929: 119829 | N929: 208908 | O929: 642929 | P929: 1639244 | Q929: 745463 | R929: 949280 | S929: 2347 | T929: 1933466 | U929: 321669 | V929: -4948 | W929: 0 | X929: 84076 | Y929: 37601 | Z929: 16087 | AA929: 10123 | AB929: 59 | AC929: 2192 | AD929: 105663 | AE929: 21746 | AF929: 38738
A930: 44055 | B930: 6957277 | C930: 11037 | D930: 5200 | E930: 1513 | F930: 6657154 | G930: 6255988 | H930: 4320093 | I930: 326044 | J930: 3681769 | K930: 275707 | L930: 36573 | M930: 116715 | N930: 222451 | O930: 632529 | P930: 1642529 | Q930: 754625 | R930: 951244 | S930: 2347 | T930: 1933548 | U930: 322962 | V930: -4880 | W930: 0 | X930: 83084 | Y930: 37734 | Z930: 16088 | AA930: 10124 | AB930: 45 | AC930: 2197 | AD930: 99782 | AE930: 21518 | AF930: 41870
A931: 44062 | B931: 7010637 | C931: 11037 | D931: 5200 | E931: 1496 | F931: 6728809 | G931: 6325788 | H931: 4345544 | I931: 326044 | J931: 3706835 | K931: 275707 | L931: 36958 | M931: 62806 | N931: 237795 | O931: 664486 | P931: 1647558 | Q931: 762621 | R931: 970278 | S931: 2347 | T931: 1977897 | U931: 325894 | V931: -5063 | W931: 0 | X931: 82190 | Y931: 37983 | Z931: 16089 | AA931: 10771 | AB931: 46 | AC931: 2197 | AD931: 95780 | AE931: 21722 | AF931: 26440
A932: 44069 | B932: 6990418 | C932: 11037 | D932: 5200 | E932: 1490 | F932: 6712320 | G932: 6310134 | H932: 4358559 | I932: 326044 | J932: 3718169 | K932: 276906 | L932: 37440 | M932: 64117 | N932: 237185 | O932: 663816 | P932: 1648650 | Q932: 771901 | R932: 972889 | S932: 2347 | T932: 1949228 | U932: 326070 | V932: -4989 | W932: 0 | X932: 81105 | Y932: 38371 | Z932: 16541 | AA932: 10771 | AB932: 45 | AC932: 2197 | AD932: 92140 | AE932: 21594 | AF932: 25521
A933: 44076 | B933: 7017492 | C933: 11037 | D933: 5200 | E933: 1477 | F933: 6741174 | G933: 6338219 | H933: 4386637 | I933: 326044 | J933: 3742629 | K933: 279915 | L933: 38049 | M933: 51692 | N933: 263002 | O933: 663688 | P933: 1662079 | Q933: 766933 | R933: 979243 | S933: 2347 | T933: 1949236 | U933: 327480 | V933: -4987 | W933: 0 | X933: 80462 | Y933: 38687 | Z933: 16542 | AA933: 11146 | AB933: 55 | AC933: 2190 | AD933: 88967 | AE933: 21714 | AF933: 25959
A934: 44083 | B934: 7010614 | C934: 11037 | D934: 5200 | E934: 1469 | F934: 6747633 | G934: 6345567 | H934: 4393621 | I934: 326044 | J934: 3747962 | K934: 281116 | L934: 38499 | M934: 42916 | N934: 279463 | O934: 656032 | P934: 1662166 | Q934: 770951 | R934: 982093 | S934: 2347 | T934: 1949599 | U934: 328660 | V934: -4958 | W934: 2 | X934: 78362 | Y934: 38899 | Z934: 16543 | AA934: 11147 | AB934: 74 | AC934: 2190 | AD934: 72069 | AE934: 21582 | AF934: 29393
... A1171: 45742 | B1171: 6740253 | C1171: 11037 | D1171: 15200 | E1171: 1569 | F1171: 6652403 | G1171: 6428765 | H1171: 4237419 | I1171: 195343 | J1171: 3612041 | K1171: 320912 | L1171: 109123 | M1171: 54915 | N1171: 216641 | O1171: 421797 | P1171: 1463220 | Q1171: 528686 | R1171: 1552159 | S1171: 2347 | T1171: 2188999 | U1171: 243307 | V1171: -23757 | W1171: 0 | X1171: 4089 | Y1171: 7285 | Z1171: 0 | AA1171: 0 | AB1171: 72 | AC1171: 596 | AD1171: 86 | AE1171: 18279 | AF1171: 33727
A1172: 45749 | B1172: 6723452 | C1172: 11037 | D1172: 15200 | E1172: 1552 | F1172: 6633702 | G1172: 6410395 | H1172: 4219049 | I1172: 195343 | J1172: 3592557 | K1172: 321443 | L1172: 109706 | M1172: 62513 | N1172: 210743 | O1172: 417119 | P1172: 1445359 | Q1172: 530587 | R1172: 1552728 | S1172: 2347 | T1172: 2188999 | U1172: 242906 | V1172: -23601 | W1172: 0 | X1172: 4001 | Y1172: 7294 | AB1172: 53 | AC1172: 583 | AD1172: 95 | AE1172: 18543 | AF1172: 35393
A1173: 45756 | B1173: 6727416 | C1173: 11037 | D1173: 15200 | E1173: 1552 | F1173: 6634362 | G1173: 6410842 | H1173: 4219496 | I1173: 195343 | J1173: 3592557 | K1173: 321443 | L1173: 110153 | M1173: 58181 | N1173: 215022 | O1173: 417235 | P1173: 1445551 | Q1173: 530638 | R1173: 1552870 | S1173: 2347 | T1173: 2188999 | U1173: 242525 | V1173: -23571 | W1173: 0 | X1173: 4566 | Y1173: 7301 | AB1173: 54 | AC1173: 586 | AD1173: 94 | AE1173: 18820 | AF1173: 38411
A1174: 45763 | B1174: 6727113 | C1174: 11037 | D1174: 15200 | E1174: 1544 | F1174: 6631602 | G1174: 6408479 | H1174: 4217259 | I1174: 195343 | J1174: 3601447 | K1174: 312055 | L1174: 108414 | M1174: 58916 | N1174: 210658 | O1174: 419053 | P1174: 1434751 | Q1174: 537198 | R1174: 1556684 | S1174: 2347 | T1174: 2188873 | U1174: 242212 | V1174: -23636 | W1174: 3 | X1174: 4544 | Y1174: 7063 | AB1174: 57 | AC1174: 573 | AD1174: 103 | AE1174: 19324 | AF1174: 40611
A1175: 45770 | B1175: 6726930 | C1175: 11037 | D1175: 15200 | E1175: 1525 | F1175: 6629422 | G1175: 6405447 | H1175: 4217694 | I1175: 195343 | J1175: 3601447 | K1175: 312055 | L1175: 108849 | M1175: 59090 | N1175: 208978 | O1175: 420627 | P1175: 1434924 | Q1175: 537249 | R1175: 1556827 | S1175: 2347 | T1175: 2185406 | U1175: 241699 | V1175: -23656 | W1175: 1000 | X1175: 4931 | Y1175: 7072 | AB1175: 59 | AC1175: 574 | AD1175: 73 | AE1175: 19290 | AF1175: 42678
A1176: 45777 | B1176: 6709277 | C1176: 11037 | D1176: 15200 | E1176: 1511 | F1176: 6613947 | G1176: 6391105 | H1176: 4215813 | I1176: 195343 | J1176: 3597415 | K1176: 313767 | L1176: 109288 | M1176: 100454 | N1176: 149087 | O1176: 451428 | P1176: 1420087 | Q1176: 536897 | R1176: 1557859 | S1176: 2347 | T1176: 2172945 | U1176: 241054 | V1176: -23625 | W1176: 111 | X1176: 5303 | Y1176: 6812 | AB1176: 76 | AC1176: 578 | AD1176: 62 | AE1176: 19402 | AF1176: 40652
A1177: 45784 | B1177: 6710889 | C1177: 11037 | D1177: 15200 | E1177: 1490 | F1177: 6612716 | G1177: 6391395 | H1177: 4216103 | I1177: 195418 | J1177: 3597415 | K1177: 313767 | L1177: 109502 | M1177: 97996 | N1177: 173191 | O1177: 429892 | P1177: 1420173 | Q1177: 536922 | R1177: 1557929 | S1177: 2347 | T1177: 2172945 | U1177: 240666 | V1177: -23621 | W1177: 7 | X1177: 4269 | Y1177: 6822 | AB1177: 77 | AC1177: 566 | AD1177: 60 | AE1177: 19261 | AF1177: 43659
A1178: 45791 | B1178: 6713270 | C1178: 11037 | D1178: 15200 | E1178: 1474 | F1178: 6612356 | G1178: 6391684 | H1178: 4216393 | I1178: 195418 | J1178: 3597490 | K1178: 313767 | L1178: 109717 | M1178: 97073 | N1178: 179232 | O1178: 424807 | P1178: 1460872 | Q1178: 496410 | R1178: 1557999 | S1178: 2347 | T1178: 2172945 | U1178: 240254 | V1178: -23582 | W1178: 1 | X1178: 3999 | Y1178: 6829 | AB1178: 52 | AC1178: 575 | AD1178: 30 | AE1178: 18971 | AF1178: 46747
A1179: 45798 | B1179: 6688726 | C1179: 11037 | D1179: 15200 | E1179: 1462 | F1179: 6604507 | G1179: 6385159 | H1179: 4213515 | I1179: 195418 | J1179: 3594399 | K1179: 313767 | L1179: 109931 | M1179: 60460 | N1179: 210420 | O1179: 412731 | P1179: 1451750 | Q1179: 511261 | R1179: 1566894 | S1179: 2347 | T1179: 2169296 | U1179: 239726 | V1179: -24032 | W1179: 1 | X1179: 3653 | Y1179: 6715 | AB1179: 75 | AC1179: 576 | AD1179: 15 | AE1179: 19258 | AF1179: 29882
A1180: 45805 | B1180: 6673244 | C1180: 11037 | D1180: 15200 | E1180: 1452 | F1180: 6591121 | G1180: 6372239 | H1180: 4213730 | I1180: 195418 | J1180: 3594399 | K1180: 313767 | L1180: 110146 | M1180: 55149 | N1180: 215142 | O1180: 413353 | P1180: 1451837 | Q1180: 511286 | R1180: 1566964 | S1180: 2347 | T1180: 2156161 | U1180: 239060 | V1180: -23990 | W1180: 1 | X1180: 3811 | Y1180: 5291 | AB1180: 72 | AC1180: 570 | AD1180: 17 | AE1180: 19138 | AF1180: 29348
A1181: 45812 | B1181: 6672885 | C1181: 11037 | D1181: 15200 | E1181: 1449 | F1181: 6589890 | G1181: 6370598 | H1181: 4212090 | I1181: 195418 | J1181: 3592490 | K1181: 313767 | L1181: 110414 | M1181: 16501 | N1181: 249879 | O1181: 417515 | P1181: 1448186 | Q1181: 510768 | R1181: 1569242 | S1181: 2347 | T1181: 2156161 | U1181: 238653 | V1181: -24031 | W1181: 1 | X1181: 4668 | Y1181: 5297 | AB1181: 43 | AC1181: 558 | AD1181: 16 | AE1181: 19396 | AF1181: 30000
A1182: 45819 | B1182: 6677155 | C1182: 11037 | D1182: 15200 | E1182: 1463 | F1182: 6591053 | G1182: 6370906 | H1182: 4212398 | I1182: 195418 | J1182: 3592490 | K1182: 313767 | L1182: 110723 | M1182: 25244 | N1182: 240733 | O1182: 417965 | P1182: 1448310 | Q1182: 510804 | R1182: 1569342 | S1182: 2347 | T1182: 2156161 | U1182: 238280 | V1182: -23897 | W1182: 0 | X1182: 5763 | Y1182: 5319 | AB1182: 55 | AC1182: 562 | AD1182: 45 | AE1182: 19404 | AF1182: 33016
A1183: 45826 | B1183: 6681056 | C1183: 11037 | D1183: 15200 | E1183: 1457 | F1183: 6591935 | G1183: 6370818 | H1183: 4212303 | I1183: 195418 | J1183: 3592043 | K1183: 313767 | L1183: 111075 | M1183: 54451 | N1183: 205803 | O1183: 421157 | P1183: 1449494 | Q1183: 511546 | R1183: 1569852 | S1183: 2347 | T1183: 2156168 | U1183: 237817 | V1183: -23844 | W1183: 0 | X1183: 7143 | Y1183: 5174 | AB1183: 51 | AC1183: 571 | AD1183: 21 | AE1183: 19441 | AF1183: 36170
... A1231: 46162 | B1231: 6713643 | C1231: 11037 | D1231: 15200 | E1231: 1405 | F1231: 6634267 | G1231: 6437719 | H1231: 4457712 | I1231: 459607 | J1231: 3615393 | K1231: 279041 | L1231: 103670 | M1231: 88919 | N1231: 343911 | O1231: 504852 | P1231: 1429880 | Q1231: 481258 | R1231: 1608892 | S1231: 2347 | T1231: 1977661 | U1231: 216518 | V1231: -25615 | W1231: 7 | X1231: 5637 | Y1231: 1420 | AB1231: 53 | AC1231: 669 | AD1231: 16 | AE1231: 19243 | AF1231: 30333

Sheet 负债
A1: 开始日期 | B1: 37257
A2: 截止日期 | B2: 当前日期
A3: EDBclose | B3: EDBclose
A4: 日期 | B4: 美国:所有联储银行:负债:总负债 | C4: 美国:所有联储银行:负债:存款 | D4: 美国:所有联储银行:负债:存款:存款机构定期存款 | E4: 美国:所有联储银行:负债:存款:存款机构其他存款 | F4: 美国:所有联储银行:负债:存款:美国财政部一般账户 | G4: 美国:所有联储银行:负债:存款:外国官方 | H4: 美国:所有联储银行:负债:存款:其他存款 | I4: 美国:所有联储银行:负债:逆向回购协议 | J4: 美国:所有联储银行:负债:联储票据(扣除美联储自持部分) | K4: 美国:所有联储银行:负债:延迟入账现金项目 | L4: 美国:所有联储银行:负债:财政部对信贷部门的捐助 | M4: 美国:所有联储银行:负债:其他负债及应计股息 | N4: 美国:所有联储银行:负债:资本账户:实缴资本 | O4: 美国:所有联储银行:负债:资本账户:结余 | P4: 美国:所有联储银行:负债:资本账户:其他资本账户 | Q4: 全部资本:净资产
A5: Date | B5: G1100086 | C5: G1100078 | D5: G1137386 | E5: G1112668 | F5: G1100080 | G5: G1100082 | H5: G1100083 | I5: G1100077 | J5: G1100076 | K5: G1100084 | L5: G1169227 | M5: G1100085 | N5: G1100087 | O5: G1100088 | P5: G1100089 | Q5: G1100090
A6: 37608 | B6: =[1]!WSD(B5:Q5,B3,B1,B2,"TradingCalendar=SSE","PriceAdj=","rptType=1","Version=1","ShowParams=Y","cols=16;rows=1223") -> 702053 | C6: 24923 | D6: 0 | E6: 17943 | F6: 6595 | G6: 172 | H6: 213 | I6: 21905 | J6: 645599 | K6: 8266 | M6: 1359 | N6: 8376 | O6: 7312 | P6: 1802 | Q6: 17489
A7: 37615 | B7: 713850 | C7: 29704 | D7: 0 | E7: 24701 | F7: 4662 | G7: 139 | H7: 203 | I7: 20396 | J7: 651891 | K7: 10447 | M7: 1413 | N7: 8382 | O7: 7312 | P7: 2516 | Q7: 18209
A8: 37622 | B8: 714234 | C8: 28249 | D8: 0 | E8: 22541 | F8: 4420 | G8: 136 | H8: 1152 | I8: 21091 | J8: 654272 | K8: 9459 | M8: 1163 | N8: 8380 | O8: 8380 | P8: 0 | Q8: 16760
A9: 37629 | B9: 706601 | C9: 31135 | D9: 0 | E9: 25196 | F9: 5490 | G9: 99 | H9: 350 | I9: 18709 | J9: 647070 | K9: 8499 | M9: 1188 | N9: 8386 | O9: 8348 | P9: 426 | Q9: 17161
A10: 37636 | B10: 702678 | C10: 32648 | D10: 0 | E10: 26991 | F10: 5192 | G10: 253 | H10: 213 | I10: 17813 | J10: 642887 | K10: 8119 | M10: 1212 | N10: 8389 | O10: 8478 | P10: 528 | Q10: 17395
A11: 37643 | B11: 718618 | C11: 44098 | D11: 0 | E11: 37629 | F11: 6119 | G11: 122 | H11: 228 | I11: 18523 | J11: 643281 | K11: 11519 | M11: 1197 | N11: 8390 | O11: 8380 | P11: 565 | Q11: 17335
A12: 37650 | B12: 695476 | C12: 25671 | D12: 0 | E12: 18327 | F12: 7030 | G12: 100 | H12: 214 | I12: 18466 | J12: 642604 | K12: 7503 | M12: 1232 | N12: 8399 | O12: 8380 | P12: 552 | Q12: 17332
A13: 37657 | B13: 702600 | C13: 29814 | D13: 0 | E13: 23756 | F13: 5664 | G13: 148 | H13: 246 | I13: 17986 | J13: 644880 | K13: 8704 | M13: 1215 | N13: 8404 | O13: 8380 | P13: 260 | Q13: 17043
A14: 37664 | B14: 696293 | C14: 21565 | D14: 0 | E14: 17707 | F14: 3527 | G14: 103 | H14: 228 | I14: 17604 | J14: 648083 | K14: 7775 | M14: 1266 | N14: 8404 | O14: 8357 | P14: 227 | Q14: 16988
A15: 37671 | B15: 712983 | C15: 32828 | D15: 0 | E15: 28006 | F15: 4407 | G15: 134 | H15: 281 | I15: 17850 | J15: 651036 | K15: 10040 | M15: 1229 | N15: 8434 | O15: 8380 | P15: 603 | Q15: 17416
A16: 37678 | B16: 704557 | C16: 28898 | D16: 0 | E16: 23556 | F16: 4950 | G16: 154 | H16: 238 | I16: 17421 | J16: 649670 | K16: 7296 | M16: 1272 | N16: 8440 | O16: 8380 | P16: 603 | Q16: 17423
A17: 37685 | B17: 705207 | C17: 26825 | D17: 0 | E17: 20980 | F17: 5501 | G17: 105 | H17: 238 | I17: 17959 | J17: 650398 | K17: 8773 | M17: 1252 | N17: 8478 | O17: 8380 | P17: 584 | Q17: 17442
A18: 37692 | B18: 699554 | C18: 21343 | D18: 0 | E18: 16219 | F18: 4775 | G18: 116 | H18: 233 | I18: 17912 | J18: 651124 | K18: 7897 | M18: 1278 | N18: 8491 | O18: 8380 | P18: 589 | Q18: 17460
... A913: 43957 | B913: 6682549 | C913: 4518539 | D913: 0 | E913: 3165606 | F913: 1143268 | G913: 16336 | H913: 193329 | I913: 265206 | J913: 1873325 | K913: 272 | M913: 25208 | N913: 32046 | O913: 6825 | P913: 0 | Q913: 38871
A914: 43964 | B914: 6895336 | C914: 4663966 | D914: 0 | E914: 3263431 | F914: 1138172 | G914: 16328 | H914: 246034 | I914: 281150 | J914: 1881319 | K914: 288 | L914: 47500 | M914: 21114 | N914: 32066 | O914: 6825 | P914: 0 | Q914: 38891
A915: 43971 | B915: 6998365 | C915: 4780812 | D915: 0 | E915: 3304221 | F915: 1193297 | G915: 16228 | H915: 267066 | I915: 266649 | J915: 1890000 | K915: 261 | L915: 49000 | M915: 11644 | N915: 32069 | O915: 6825 | P915: 0 | Q915: 38894
A916: 43978 | B916: 7058402 | C916: 4839897 | D916: 0 | E916: 3317688 | F916: 1326897 | G916: 16251 | H916: 179062 | I916: 243976 | J916: 1899514 | K916: 355 | L916: 66500 | M916: 8160 | N916: 32089 | O916: 6825 | P916: 0 | Q916: 38914
A917: 43985 | B917: 7126300 | C917: 4860697 | D917: 0 | E917: 3257435 | F917: 1431462 | G917: 16281 | H917: 155519 | I917: 246054 | J917: 1903660 | K917: 758 | L917: 104000 | M917: 11131 | N917: 32092 | O917: 6825 | P917: 0 | Q917: 38917
A918: 43992 | B918: 7130021 | C918: 4867282 | D918: 0 | E918: 3190654 | F918: 1504569 | G918: 16256 | H918: 155802 | I918: 240814 | J918: 1907027 | K918: 277 | L918: 104000 | M918: 10621 | N918: 32091 | O918: 6825 | P918: 0 | Q918: 38916
A919: 43999 | B919: 7055776 | C919: 4795630 | D919: 0 | E919: 3069439 | F919: 1565306 | G919: 16247 | H919: 144637 | I919: 225462 | J919: 1910886 | K919: 268 | L919: 114000 | M919: 9531 | N919: 32090 | O919: 6825 | P919: 0 | Q919: 38915
A920: 44006 | B920: 7043391 | C920: 4786037 | D920: 0 | E920: 2937657 | F920: 1586573 | G920: 16222 | H920: 245586 | I920: 220362 | J920: 1915107 | K920: 285 | L920: 114000 | M920: 7599 | N920: 32086 | O920: 6825 | P920: 0 | Q920: 38911
A921: 44013 | B921: 6970195 | C921: 4698086 | D921: 0 | E921: 2863196 | F921: 1656747 | G921: 16223 | H921: 161920 | I921: 227236 | J921: 1922987 | K921: 801 | L921: 114000 | M921: 7084 | N921: 32020 | O921: 6825 | P921: 0 | Q921: 38845
A922: 44020 | B922: 6881955 | C922: 4604866 | D922: 0 | E922: 2813296 | F922: 1624404 | G922: 16232 | H922: 150934 | I922: 224860 | J922: 1928475 | K922: 266 | L922: 114000 | M922: 9487 | N922: 31936 | O922: 6825 | P922: 0 | Q922: 38761
A923: 44027 | B923: 6919843 | C923: 4637969 | D923: 0 | E923: 2732649 | F923: 1740455 | G923: 16232 | H923: 148633 | I923: 224229 | J923: 1932779 | K923: 280 | L923: 114000 | M923: 10586 | N923: 31936 | O923: 6825 | P923: 0 | Q923: 38761
A924: 44034 | B924: 6925994 | C924: 4650895 | D924: 0 | E924: 2659658 | F924: 1777180 | G924: 16224 | H924: 197833 | I924: 214665 | J924: 1937015 | K924: 307 | L924: 114000 | M924: 9113 | N924: 31936 | O924: 6825 | P924: 0 | Q924: 38761
A925: 44041 | B925: 6910241 | C925: 4626079 | D925: 0 | E925: 2685376 | F925: 1792434 | G925: 16224 | H925: 132045 | I925: 217053 | J925: 1943979 | K925: 989 | L925: 114000 | M925: 8141 | N925: 31966 | O925: 6825 | P925: 0 | Q925: 38791
... A1228: 46162 | B1228: 6666407 | C1228: 4144576 | D1228: 0 | E1228: 3106716 | F1228: 781979 | G1228: 9443 | H1228: 246438 | I1228: 342628 | J1228: 2410379 | K1228: 316 | L1228: 821 | M1228: -232314 | N1228: 40451 | O1228: 6785 | P1228: 0 | Q1228: 47236
